Workbook

Sheet Lisez-moi
A1: Zones commerciales périphériques, centres-villes et QPV : base de chiffres pour l'état de l'art
A2: Étude de cas France, OCDE (division PME). Version du 1er octobre 2026.
A4: Objet | B4: Rassembler les chiffres publiés sur le développement des zones commerciales périphériques et sur la situation des centres-villes et des QPV. Les chiffres ne sont pas comparés ni combinés entre eux : chacun est rattaché à sa source, à son année et à ce qu'il mesure.
A5: Onglet « Chiffres » | B5: Un chiffre par ligne. Filtrer par thème, par source ou par niveau de vérification avec les flèches de l'en-tête.
A6: Onglet « Sources » | B6: Liste des documents, avec le nombre de chiffres repris dans l'onglet « Chiffres » (calculé automatiquement).
A7: Onglet « Données manquantes » | B7: Données et documents qui manquent pour évaluer pleinement l'influence des zones périphériques sur les centres-villes et les QPV, avec le détenteur, l'accès et une démarche suggérée.
A8: Onglet « Calculs propres (Sirene) » | B8: Nos propres calculs sur le répertoire Sirene (2012-2025). Ce ne sont pas des chiffres publiés : à présenter séparément de l'état de l'art.
A9: Onglet « Synthèse » | B9: Décompte des chiffres par thème et par niveau de vérification (formules).
A11: Colonnes de l'onglet « Chiffres »
A12: Indicateur | B12: Ce qui est mesuré, formulé de façon à être compris hors contexte.
A13: Valeur / Unité | B13: Valeur telle que publiée. Les pourcentages sont saisis en points (65 = 65 %). Une valeur textuelle signale une fourchette ou un ratio.
A14: Année(s) de référence | B14: Année ou période à laquelle se rapporte le chiffre (et non l'année de publication).
A15: Territoire | B15: Champ géographique couvert.
A16: Ce que le chiffre prend en compte | B16: Définition, champ statistique, panel : c'est la colonne à lire avant de rapprocher deux chiffres.
A17: Vérification | B17: Niveau de confiance dans la reprise du chiffre (voir légende ci-dessous).
A19: Légende : vérification
A20: A - Relu dans la source primaire | B20: Chiffre relu le 1er octobre 2026 dans le document cité en source (seconde vérification). Pour une source qui est elle-même un relais, voir le niveau C.
A21: B - Source primaire consultée pendant la recherche (non relue) | B21: Chiffre relevé sur la page ou le document d'origine pendant la recherche documentaire, sans nouvelle relecture.
A22: C - Via un relais (presse, synthèse, autre rapport) | B22: Chiffre lu dans un document qui cite la source d'origine (article de presse, synthèse, autre rapport).
A23: D - Non vérifié : origine à confirmer | B23: Origine du chiffre non identifiée ou chiffre issu d'une synthèse automatique : à vérifier avant toute citation.
A24: E - Repris de la présentation OCDE (non revérifié) | B24: Chiffre repris de la présentation OCDE (diapositives), avec les sources indiquées sur la diapositive, non revérifié ici.
A26: Ajouter un chiffre | B26: Insérer une ligne dans l'onglet « Chiffres », renseigner toutes les colonnes et utiliser une référence de l'onglet « Sources » (ajouter la source si elle est nouvelle). Les listes déroulantes « Thème », « Type de source » et « Vérification » garantissent des catégories homogènes.
A27: Seconde vérification | B27: Le 1er octobre 2026, chaque source a été retéléchargée et chaque chiffre recherché dans son texte. Les corrections (année, valeur, intitulé) et les chiffres introuvables (passés au niveau D) sont détaillés dans la colonne « Remarques ». La même base est consultable et modifiable en ligne dans le « Registre du commerce périphérique ».
A28: Précautions | B28: Plusieurs indicateurs proches ont des champs différents (ex. vacance « tous sites », « rues marchandes », « centres-villes ACV » ; surfaces CDAC selon la CNAC ou selon Kyris / Procos). Comparer uniquement des chiffres de même champ et de même source.

Sheet Chiffres
A1: Chiffres publiés
A2: Un chiffre par ligne. Pourcentages saisis en points (65 = 65 %).
A4: N° | B4: Thème | C4: Indicateur | D4: Valeur | E4: Unité | F4: Année(s) de référence | G4: Territoire | H4: Ce que le chiffre prend en compte (champ, définition) | I4: Réf. source | J4: Source | K4: Date de publication | L4: Type de source | M4: Vérification | N4: Lien | O4: Remarques
A5: 1 | B5: 1. Poids des zones commerciales périphériques | C5: Nombre de zones commerciales de périphérie | D5: 1500 | E5: zones | F5: 2022-2023 | G5: France | H5: Inventaire national du Cerema (photo-interprétation et fichiers fonciers). Ordre de grandeur : « 1 500 zones recensées ». | I5: S01 | J5: Cerema, Accompagner la mutation des zones commerciales de périphérie | K5: 19/05/2025 | L5: Administration / opérateur public | M5: A - Relu dans la source primaire | N5: https://www.cerema.fr/fr/actualites/accompagner-mutation-zones-commerciales-peripherie
A6: 2 | B6: 1. Poids des zones commerciales périphériques | C6: Surface couverte par ces zones | D6: 500 | E6: millions de m² | F6: 2022-2023 | G6: France | H6: Emprise des zones (« cinq fois la superficie de Paris »). Ne correspond pas à la surface de vente : inclut vraisemblablement bâti, parkings et voiries. | I6: S01 | J6: Cerema, Accompagner la mutation des zones commerciales de périphérie | K6: 19/05/2025 | L6: Administration / opérateur public | M6: A - Relu dans la source primaire | N6: https://www.cerema.fr/fr/actualites/accompagner-mutation-zones-commerciales-peripherie | O6: Même chiffre dans le dossier de presse du Gouvernement (S08).
A7: 3 | B7: 1. Poids des zones commerciales périphériques | C7: Nombre de contours retenus dans la base EmpCom | D7: 1527 | E7: contours | F7: inventaire 2022, publié 02/2023 | G7: France métropolitaine | H7: Emprises de plus de 20 000 m² de surface bâtie, et surface commerciale > 60 000 m² ou entre 25 000 et 150 000 m² avec > 15 000 m² de surface commerciale. | I7: S02 | J7: Cerema, Les données de géolocalisation des 1500 zones commerciales de périphérie sont en open data (base EmpCom) | K7: 23/01/2024 | L7: Administration / opérateur public | M7: A - Relu dans la source primaire | N7: https://www.cerema.fr/fr/actualites/donnees-geolocalisation-1500-zones-commerciales-peripherie | O7: Base en open data (DataFoncier, data.gouv.fr).
A8: 4 | B8: 1. Poids des zones commerciales périphériques | C8: Part des déplacements en voiture vers les zones commerciales périphériques, métropoles | D8: 84 | E8: % | F8: s.d. | G8: Métropoles | H8: Part de la voiture individuelle dans les déplacements à destination des zones commerciales périphériques. | I8: S01 | J8: Cerema, Accompagner la mutation des zones commerciales de périphérie | K8: 19/05/2025 | L8: Administration / opérateur public | M8: A - Relu dans la source primaire | N8: https://www.cerema.fr/fr/actualites/accompagner-mutation-zones-commerciales-peripherie | O8: Source de l'enquête de mobilité non précisée sur la page.
A9: 5 | B9: 1. Poids des zones commerciales périphériques | C9: Part des déplacements en voiture vers les zones commerciales périphériques, villes moyennes | D9: 88 | E9: % | F9: s.d. | G9: Villes moyennes | H9: Idem, villes moyennes. | I9: S01 | J9: Cerema, Accompagner la mutation des zones commerciales de périphérie | K9: 19/05/2025 | L9: Administration / opérateur public | M9: A - Relu dans la source primaire | N9: https://www.cerema.fr/fr/actualites/accompagner-mutation-zones-commerciales-peripherie
A10: 6 | B10: 1. Poids des zones commerciales périphériques | C10: Part de la surface commerciale des pôles située dans les pôles de périphérie | D10: 65 | E10: % | F10: 2015 | G10: France métropolitaine et La Réunion | H10: Pôles du commerce de proximité au sens de l'Insee (commerce de détail + services de la vie courante). Les pôles de périphérie représentent 23 % des établissements des pôles. | I10: S05 | J10: Bédué M. et Cohen C. (Insee), Le commerce de proximité : des pôles plus florissants en périphérie qu'en centre-ville, Insee Première n° 1858 | K10: 20/05/2021 | L10: Statistique publique | M10: A - Relu dans la source primaire | N10: https://www.insee.fr/fr/statistiques/5386414 | O10: Le résumé de la publication dit « deux tiers ». Ne pas citer 66 %.
A11: 7 | B11: 1. Poids des zones commerciales périphériques | C11: Part de l'emploi salarié des pôles située dans les pôles de périphérie | D11: 45 | E11: % | F11: 2015 | G11: France métropolitaine et La Réunion | H11: Même champ (pôles du commerce de proximité). | I11: S05 | J11: Bédué M. et Cohen C. (Insee), Le commerce de proximité : des pôles plus florissants en périphérie qu'en centre-ville, Insee Première n° 1858 | K11: 20/05/2021 | L11: Statistique publique | M11: A - Relu dans la source primaire | N11: https://www.insee.fr/fr/statistiques/5386414
A12: 8 | B12: 1. Poids des zones commerciales périphériques | C12: Nombre de pôles du commerce de proximité | D12: 7951 | E12: pôles | F12: 2015 | G12: France métropolitaine et La Réunion | H12: Pôles identifiés par l'Insee ; 62 % sont des pôles de périphérie. | I12: S05 | J12: Bédué M. et Cohen C. (Insee), Le commerce de proximité : des pôles plus florissants en périphérie qu'en centre-ville, Insee Première n° 1858 | K12: 20/05/2021 | L12: Statistique publique | M12: A - Relu dans la source primaire | N12: https://www.insee.fr/fr/statistiques/5386414
A13: 9 | B13: 1. Poids des zones commerciales périphériques | C13: Part des salariés des points de vente aux ménages travaillant dans les pôles de périphérie | D13: 37 | E13: % | F13: 2022 | G13: France | H13: Points de vente aux ménages ; les pôles de centre-ville rassemblent aussi 37 % des salariés (1,0 million). | I13: S07 | J13: Bloch K. et Pichavant A.-S. (Insee), Entre 2016 et 2022, l'emploi salarié des points de vente progresse davantage en dehors des centres-villes, Insee Première n° 2091 | K13: 27/01/2026 | L13: Statistique publique | M13: A - Relu dans la source primaire | N13: https://www.insee.fr/fr/statistiques/8730497 | O13: Champ et définition des pôles différents de l'Insee Première n° 1858.
A14: 10 | B14: 1. Poids des zones commerciales périphériques | C14: Taille moyenne d'un point de vente en pôle de périphérie | D14: 586 | E14: m² de surface de vente | F14: 2022 | G14: France | H14: Moyenne par point de vente ; 12 salariés en moyenne ; 26 établissements par pôle en moyenne. | I14: S07 | J14: Bloch K. et Pichavant A.-S. (Insee), Entre 2016 et 2022, l'emploi salarié des points de vente progresse davantage en dehors des centres-villes, Insee Première n° 2091 | K14: 27/01/2026 | L14: Statistique publique | M14: A - Relu dans la source primaire | N14: https://www.insee.fr/fr/statistiques/8730497
A15: 11 | B15: 1. Poids des zones commerciales périphériques | C15: Taille moyenne d'un point de vente en pôle de centre-ville | D15: 92 | E15: m² de surface de vente | F15: 2022 | G15: France | H15: Moyenne par point de vente ; 3 salariés en moyenne ; 108 établissements par pôle en moyenne. | I15: S07 | J15: Bloch K. et Pichavant A.-S. (Insee), Entre 2016 et 2022, l'emploi salarié des points de vente progresse davantage en dehors des centres-villes, Insee Première n° 2091 | K15: 27/01/2026 | L15: Statistique publique | M15: A - Relu dans la source primaire | N15: https://www.insee.fr/fr/statistiques/8730497
A16: 12 | B16: 1. Poids des zones commerciales périphériques | C16: Part des dépenses des Français en magasin réalisées dans les entrées de ville / zones commerciales | D16: 72 | E16: % | F16: s.d. (dossier 2023) | G16: France | H16: Dépenses en magasin (hors internet). Centre-ville : 15 % ; espaces « interstices » (ruralité, banlieue dense) : 13 %. | I16: S08 | J16: Gouvernement (ministères Économie, Transition écologique, Cohésion des territoires), Un nouvel horizon pour les zones commerciales, dossier de presse | K16: 09/2023 | L16: Administration / opérateur public | M16: A - Relu dans la source primaire | N16: https://www.info.gouv.fr/upload/media/content/0001/07/2dc90efc2c1a0e97572bf027240fac63e4dc9d75.pdf | O16: La source statistique d'origine n'est pas donnée (renvoi en note non détaillé). Aussi relayé par LSA Conso (S44).
A17: 13 | B17: 1. Poids des zones commerciales périphériques | C17: Part des dépenses en magasin réalisées en centre-ville | D17: 15 | E17: % | F17: s.d. (dossier 2023) | G17: France | H17: Même champ que la ligne précédente. | I17: S08 | J17: Gouvernement (ministères Économie, Transition écologique, Cohésion des territoires), Un nouvel horizon pour les zones commerciales, dossier de presse | K17: 09/2023 | L17: Administration / opérateur public | M17: A - Relu dans la source primaire | N17: https://www.info.gouv.fr/upload/media/content/0001/07/2dc90efc2c1a0e97572bf027240fac63e4dc9d75.pdf
A18: 14 | B18: 1. Poids des zones commerciales périphériques | C18: Part du chiffre d'affaires du commerce de détail réalisée dans les lieux de commerce de périphérie | D18: 70 | E18: % (plus de) | F18: s.d. (dossier 2025) | G18: France | H18: Chiffre d'affaires du commerce de détail, selon Procos. | I18: S09 | J18: Procos, Dossier de presse, conférence annuelle | K18: 12/02/2025 | L18: Fédération ou cabinet privé | M18: A - Relu dans la source primaire | N18: https://www.procos.org/images/procos/presse/2025/Conf_0225/procos_dp_120225_site.pdf | O18: Formulé « plus de 70 % » sans détail de méthode.
A19: 15 | B19: 1. Poids des zones commerciales périphériques | C19: Part de marché du commerce de détail des quelque 1 500 zones commerciales | D19: 75 | E19: % | F19: 2020 | G19: France | H19: Parts de marché du commerce de détail (source Procos, 2020, citée par le Cerema). | I19: S03 | J19: Cerema, Zones commerciales et centres-villes : trouver le bon équilibre | K19: s.d. (vers 2020-2021) | L19: Administration / opérateur public | M19: C - Via un relais (presse, synthèse, autre rapport) | N19: https://www.cerema.fr/fr/actualites/zones-commerciales-centres-villes-trouver-bon-equilibre | O19: Lu sur la page Cerema ; la publication Procos d'origine n'a pas été consultée.
A20: 16 | B20: 1. Poids des zones commerciales périphériques | C20: Part des ventes du commerce de détail réalisées en périphérie | D20: 67 | E20: % | F20: 2024 | G20: France | H20: Ensemble des ventes du commerce de détail, internet compris. | I20: S13 | J20: Rexecode, Répartition des ventes du commerce de détail par lieu de vente, d'après Insee, Procos et Fevad | K20: 2024 | L20: Fédération ou cabinet privé | M20: E - Repris de la présentation OCDE (non revérifié) | O20: Répartition : périphérie 67 %, centre-ville 11 %, proximité 11 %, internet 11 %.
A21: 17 | B21: 1. Poids des zones commerciales périphériques | C21: Part des ventes du commerce de détail réalisées en centre-ville | D21: 11 | E21: % | F21: 2024 | G21: France | H21: Même champ (internet compris). | I21: S13 | J21: Rexecode, Répartition des ventes du commerce de détail par lieu de vente, d'après Insee, Procos et Fevad | K21: 2024 | L21: Fédération ou cabinet privé | M21: E - Repris de la présentation OCDE (non revérifié)
A22: 18 | B22: 1. Poids des zones commerciales périphériques | C22: Part des ventes du commerce de détail réalisées sur internet | D22: 11 | E22: % | F22: 2024 | G22: France | H22: Même champ. | I22: S13 | J22: Rexecode, Répartition des ventes du commerce de détail par lieu de vente, d'après Insee, Procos et Fevad | K22: 2024 | L22: Fédération ou cabinet privé | M22: E - Repris de la présentation OCDE (non revérifié)
A23: 19 | B23: 1. Poids des zones commerciales périphériques | C23: Évolution des surfaces commerciales entre 2000 et 2020 | D23: x 2 | E23: multiplicateur | F23: 2000-2020 | G23: France | H23: Doublement des surfaces commerciales sans hausse équivalente des dépenses des ménages (« obésité commerciale »). | I23: S22 | J23: Sénat, mission conjointe de contrôle, Revitalisation des centres-villes et des centres-bourgs : entre enthousiasme et frustrations, rapport d'information n° 910 (2021-2022) | K23: 2022 | L23: Rapport institutionnel (Cour des comptes, Parlement, inspections, mission) | M23: D - Non vérifié : origine à confirmer | N23: https://www.senat.fr/rap/r21-910/r21-9109.html | O23: Seconde vérification (01/10/2026) : non retrouvé dans le chapitre consulté du rapport n° 910. Le rapport parle d'« obésité commerciale » en citant Pascal Madry (« il y a trop de m² en France »).
A24: 20 | B24: 1. Poids des zones commerciales périphériques | C24: Distance moyenne entre zones commerciales et centre-ville | D24: 3.2 | E24: km | F24: s.d. | G24: France | H24: Distance moyenne des plus de 1 500 zones aux centres-villes. | I24: S44 | J24: LSA Conso, La périphérie urbaine aimante le commerce | K24: s.d. | L24: Presse / média spécialisé | M24: D - Non vérifié : origine à confirmer | N24: https://www.lsa-conso.fr/la-peripherie-urbaine-aimante-le-commerce,323561 | O24: Article de presse ; méthode et source d'origine non identifiées.
A25: 21 | B25: 2. Centres-villes : emploi et établissements | C25: Croissance annuelle de l'emploi salarié dans les pôles de périphérie | D25: 2.3 | E25: % par an | F25: 2009-2015 | G25: France métropolitaine et La Réunion | H25: Emploi salarié du commerce de proximité dans les pôles de périphérie. | I25: S05 | J25: Bédué M. et Cohen C. (Insee), Le commerce de proximité : des pôles plus florissants en périphérie qu'en centre-ville, Insee Première n° 1858 | K25: 20/05/2021 | L25: Statistique publique | M25: A - Relu dans la source primaire | N25: https://www.insee.fr/fr/statistiques/5386414
A26: 22 | B26: 2. Centres-villes : emploi et établissements | C26: Croissance annuelle de l'emploi salarié dans les pôles de centre-ville | D26: 0.2 | E26: % par an | F26: 2009-2015 | G26: France métropolitaine et La Réunion | H26: Même champ, pôles de centre-ville (« stabilité »). | I26: S05 | J26: Bédué M. et Cohen C. (Insee), Le commerce de proximité : des pôles plus florissants en périphérie qu'en centre-ville, Insee Première n° 1858 | K26: 20/05/2021 | L26: Statistique publique | M26: A - Relu dans la source primaire | N26: https://www.insee.fr/fr/statistiques/5386414 | O26: La note du CAE (S12) écrit « a baissé de 0,2 % » : l'Insee indique +0,2 %.
A27: 23 | B27: 2. Centres-villes : emploi et établissements | C27: Évolution annuelle de l'emploi du commerce de proximité hors pôles | D27: -1.2 | E27: % par an | F27: 2009-2015 | G27: France métropolitaine et La Réunion | H27: Commerces isolés, hors pôles commerciaux. | I27: S05 | J27: Bédué M. et Cohen C. (Insee), Le commerce de proximité : des pôles plus florissants en périphérie qu'en centre-ville, Insee Première n° 1858 | K27: 20/05/2021 | L27: Statistique publique | M27: A - Relu dans la source primaire | N27: https://www.insee.fr/fr/statistiques/5386414
A28: 24 | B28: 2. Centres-villes : emploi et établissements | C28: Part des pôles de centre-ville où l'emploi salarié baisse | D28: 38 | E28: % | F28: 2009-2015 | G28: France métropolitaine et La Réunion | H28: Contre 23 % des pôles de périphérie. | I28: S05 | J28: Bédué M. et Cohen C. (Insee), Le commerce de proximité : des pôles plus florissants en périphérie qu'en centre-ville, Insee Première n° 1858 | K28: 20/05/2021 | L28: Statistique publique | M28: A - Relu dans la source primaire | N28: https://www.insee.fr/fr/statistiques/5386414
A29: 25 | B29: 2. Centres-villes : emploi et établissements | C29: Part des pôles de périphérie où l'emploi salarié baisse | D29: 23 | E29: % | F29: 2009-2015 | G29: France métropolitaine et La Réunion | I29: S05 | J29: Bédué M. et Cohen C. (Insee), Le commerce de proximité : des pôles plus florissants en périphérie qu'en centre-ville, Insee Première n° 1858 | K29: 20/05/2021 | L29: Statistique publique | M29: A - Relu dans la source primaire | N29: https://www.insee.fr/fr/statistiques/5386414
A30: 26 | B30: 2. Centres-villes : emploi et établissements | C30: EPCI où l'emploi des pôles de périphérie croît de plus de 1 %/an : part où l'emploi des centres-villes baisse de plus de 1 %/an | D30: 46 | E30: % | F30: 2009-2015 | G30: France métropolitaine et La Réunion | H30: Croisement par EPCI de l'évolution de l'emploi des pôles de périphérie et de centre-ville. | I30: S05 | J30: Bédué M. et Cohen C. (Insee), Le commerce de proximité : des pôles plus florissants en périphérie qu'en centre-ville, Insee Première n° 1858 | K30: 20/05/2021 | L30: Statistique publique | M30: A - Relu dans la source primaire | N30: https://www.insee.fr/fr/statistiques/5386414 | O30: Quand la périphérie recule d'au moins 1 %/an, la part est de 43 %.
A31: 27 | B31: 2. Centres-villes : emploi et établissements | C31: Pôles de centre-ville en baisse d'emploi dans les aires en recul démographique | D31: 57 | E31: % | F31: 2009-2015 | G31: France métropolitaine et La Réunion | H31: Pôles où l'emploi salarié « se replie nettement » ; 30 % dans les aires les plus dynamiques. | I31: S05 | J31: Bédué M. et Cohen C. (Insee), Le commerce de proximité : des pôles plus florissants en périphérie qu'en centre-ville, Insee Première n° 1858 | K31: 20/05/2021 | L31: Statistique publique | M31: A - Relu dans la source primaire | N31: https://www.insee.fr/fr/statistiques/5386414 | O31: Pour les pôles de périphérie : 27 % contre 18 %.
A32: 28 | B32: 2. Centres-villes : emploi et établissements | C32: Part des centres-villes de villes de taille intermédiaire (VTI) en baisse tendancielle d'emploi | D32: 82 | E32: % | F32: 2009-2015 | G32: 368 villes de taille intermédiaire | H32: Emploi salarié du commerce de proximité en centre-ville. | I32: S06 | J32: Cazaubiel A. et Guymarc G. (Insee), Commerce de proximité dans les villes de taille intermédiaire, Insee Première n° 1782 | K32: 14/11/2019 | L32: Statistique publique | M32: A - Relu dans la source primaire | N32: https://www.insee.fr/fr/statistiques/4248184 | O32: Dans la moitié des VTI, la baisse dépasse 1,4 % par an.
A33: 29 | B33: 2. Centres-villes : emploi et établissements | C33: Établissements détruits chaque année dans les centres-villes des VTI | D33: 600 | E33: établissements par an | F33: 2009-2015 | G33: 368 VTI | H33: Commerce de proximité, centres-villes. | I33: S06 | J33: Cazaubiel A. et Guymarc G. (Insee), Commerce de proximité dans les villes de taille intermédiaire, Insee Première n° 1782 | K33: 14/11/2019 | L33: Statistique publique | M33: A - Relu dans la source primaire | N33: https://www.insee.fr/fr/statistiques/4248184 | O33: Dans le même temps, les agglomérations gagnent 100 établissements par an.
A34: 30 | B34: 2. Centres-villes : emploi et établissements | C34: Emplois salariés détruits chaque année dans les centres-villes des VTI | D34: 3500 | E34: emplois par an | F34: 2009-2015 | G34: 368 VTI | H34: Commerce de proximité, centres-villes. | I34: S06 | J34: Cazaubiel A. et Guymarc G. (Insee), Commerce de proximité dans les villes de taille intermédiaire, Insee Première n° 1782 | K34: 14/11/2019 | L34: Statistique publique | M34: A - Relu dans la source primaire | N34: https://www.insee.fr/fr/statistiques/4248184 | O34: Dans le même temps, les agglomérations gagnent 1 600 salariés par an.
A35: 31 | B35: 2. Centres-villes : emploi et établissements | C35: Part des VTI où l'emploi baisse en centre-ville mais augmente dans l'agglomération | D35: 37 | E35: % | F35: 2009-2015 | G35: 368 VTI | I35: S06 | J35: Cazaubiel A. et Guymarc G. (Insee), Commerce de proximité dans les villes de taille intermédiaire, Insee Première n° 1782 | K35: 14/11/2019 | L35: Statistique publique | M35: A - Relu dans la source primaire | N35: https://www.insee.fr/fr/statistiques/4248184
A36: 32 | B36: 2. Centres-villes : emploi et établissements | C36: Croissance annuelle de l'emploi salarié des points de vente, pôles de centre-ville | D36: 1.1 | E36: % par an | F36: 2016-2022 | G36: France | H36: Points de vente aux ménages (commerce de détail, restauration, services). | I36: S07 | J36: Bloch K. et Pichavant A.-S. (Insee), Entre 2016 et 2022, l'emploi salarié des points de vente progresse davantage en dehors des centres-villes, Insee Première n° 2091 | K36: 27/01/2026 | L36: Statistique publique | M36: A - Relu dans la source primaire | N36: https://www.insee.fr/fr/statistiques/8730497 | O36: +1,0 % hors bassin de vie de Paris.
A37: 33 | B37: 2. Centres-villes : emploi et établissements | C37: Croissance annuelle de l'emploi salarié des points de vente, pôles de périphérie | D37: 1.6 | E37: % par an | F37: 2016-2022 | G37: France | H37: Même champ. Nombre d'établissements +1,7 %/an, surface de vente +1,3 %/an. | I37: S07 | J37: Bloch K. et Pichavant A.-S. (Insee), Entre 2016 et 2022, l'emploi salarié des points de vente progresse davantage en dehors des centres-villes, Insee Première n° 2091 | K37: 27/01/2026 | L37: Statistique publique | M37: A - Relu dans la source primaire | N37: https://www.insee.fr/fr/statistiques/8730497
A38: 34 | B38: 2. Centres-villes : emploi et établissements | C38: Croissance annuelle de l'emploi salarié des points de vente hors pôles | D38: 1.9 | E38: % par an | F38: 2016-2022 | G38: France | H38: Même champ. | I38: S07 | J38: Bloch K. et Pichavant A.-S. (Insee), Entre 2016 et 2022, l'emploi salarié des points de vente progresse davantage en dehors des centres-villes, Insee Première n° 2091 | K38: 27/01/2026 | L38: Statistique publique | M38: A - Relu dans la source primaire | N38: https://www.insee.fr/fr/statistiques/8730497
A39: 35 | B39: 2. Centres-villes : emploi et établissements | C39: Contribution des pôles de périphérie à la hausse de l'emploi salarié des points de vente | D39: 40 | E39: % | F39: 2016-2022 | G39: France | H39: Hausse totale : +235 000 salariés (+1,5 %/an). Contribution des pôles de centre-ville : 28 %. | I39: S07 | J39: Bloch K. et Pichavant A.-S. (Insee), Entre 2016 et 2022, l'emploi salarié des points de vente progresse davantage en dehors des centres-villes, Insee Première n° 2091 | K39: 27/01/2026 | L39: Statistique publique | M39: A - Relu dans la source primaire | N39: https://www.insee.fr/fr/statistiques/8730497
A40: 36 | B40: 2. Centres-villes : emploi et établissements | C40: Évolution annuelle de l'emploi salarié dans le commerce de détail d'habillement | D40: -2.2 | E40: % par an | F40: 2016-2022 | G40: France | H40: Ensemble des points de vente. Nombre d'établissements d'habillement : −14,9 % sur la période. | I40: S07 | J40: Bloch K. et Pichavant A.-S. (Insee), Entre 2016 et 2022, l'emploi salarié des points de vente progresse davantage en dehors des centres-villes, Insee Première n° 2091 | K40: 27/01/2026 | L40: Statistique publique | M40: A - Relu dans la source primaire | N40: https://www.insee.fr/fr/statistiques/8730497 | O40: Équipement de la personne hors biens médicaux : −1,6 %/an.
A41: 37 | B41: 2. Centres-villes : emploi et établissements | C41: Entreprises du commerce de proximité | D41: 700000 | E41: entreprises (environ) | F41: non précisée (rapport 2023) | G41: France | H41: Champ de la Cour : commerces alimentaires spécialisés (épiceries, cavistes, primeurs), artisanat commercial (boulangeries, boucheries) et services (coiffure, soins). 1,1 million d'emplois salariés et non salariés ; 68 % sans salarié, 12 % avec plus de trois salariés ; chiffre d'affaires moyen de 223 000 €. | I41: S23 | J41: Cour des comptes, La politique de l'État en faveur du commerce de proximité, rapport public thématique (période 2017-2022) | K41: 29/09/2023 | L41: Rapport institutionnel (Cour des comptes, Parlement, inspections, mission) | M41: A - Relu dans la source primaire | N41: https://www.ccomptes.fr/sites/default/files/2023-10/20230929-politiques-publiques-commerce-proximite.pdf | O41: Relu dans le rapport (p. 20-21). N'inclut pas l'ensemble du commerce de détail.
A42: 38 | B42: 2. Centres-villes : emploi et établissements | C42: Nombre d'établissements du petit commerce | D42: 430000 | E42: établissements | F42: 2019 | G42: France | H42: Petit commerce au sens large du CAE (commerce de détail hors grandes surfaces, bars, restaurants, services aux ménages) ; environ 12 % de l'emploi total et 6 % du PIB. | I42: S12 | J42: Allain M.-L. et Epaulard A. (CAE), Petits commerces : déclin ou mutation ?, Les notes du CAE n° 77 | K42: 05/2023 | L42: Recherche académique / CAE | M42: A - Relu dans la source primaire | N42: https://www.cae-eco.fr/
A43: 39 | B43: 3. Centres-villes : vacance commerciale | C43: Taux de vacance commerciale en centre-ville | D43: 6 | E43: % | F43: 2001 | G43: 187 centres-villes (panel CGEDD) | H43: Vacance commerciale, panel de 187 centres-villes. | I43: S18 | J43: Public Sénat, citant un rapport du CGEDD (2016), Revitalisation des centres-villes : un rapport du Sénat pointe un sous-financement | K43: 2022 | L43: Presse / média spécialisé | M43: D - Non vérifié : origine à confirmer | N43: https://www.publicsenat.fr/actualites/territoires/revitalisation-des-centres-villes-un-rapport-du-senat-pointe-un-sous | O43: Seconde vérification (01/10/2026) : chiffre non retrouvé dans l'article de Public Sénat, qui mentionne seulement une hausse d'un point depuis 2019 dans les villes ACV.
A44: 40 | B44: 3. Centres-villes : vacance commerciale | C44: Taux de vacance commerciale en centre-ville | D44: 10 | E44: % (plus de) | F44: 2015 | G44: 187 centres-villes (panel CGEDD) | H44: Idem. | I44: S18 | J44: Public Sénat, citant un rapport du CGEDD (2016), Revitalisation des centres-villes : un rapport du Sénat pointe un sous-financement | K44: 2022 | L44: Presse / média spécialisé | M44: D - Non vérifié : origine à confirmer | N44: https://www.publicsenat.fr/actualites/territoires/revitalisation-des-centres-villes-un-rapport-du-senat-pointe-un-sous | O44: Seconde vérification (01/10/2026) : chiffre non retrouvé dans l'article de Public Sénat, qui mentionne seulement une hausse d'un point depuis 2019 dans les villes ACV.
A45: 41 | B45: 3. Centres-villes : vacance commerciale | C45: Part des centres-villes où la vacance augmente | D45: 87 | E45: % | F45: période d'étude du rapport (avant 2016) | G45: 900 centres-villes | H45: Rapport interministériel CGEDD / IGF. | I45: S19 | J45: CGEDD et IGF (cité par le Cerema), Rapport interministériel sur la revitalisation commerciale des centres-villes | K45: 2016 | L45: Rapport institutionnel (Cour des comptes, Parlement, inspections, mission) | M45: D - Non vérifié : origine à confirmer | N45: https://www.cerema.fr/fr/actualites/zones-commerciales-centres-villes-trouver-bon-equilibre | O45: Seconde vérification (01/10/2026) : non retrouvé sur la page du Cerema citée ; origine à établir.
A46: 42 | B46: 3. Centres-villes : vacance commerciale | C46: Taux de vacance commerciale en centre-ville | D46: 11.3 | E46: % | F46: 2016 | G46: Centres-villes des agglomérations de plus de 25 000 habitants | H46: Selon l'Institut pour la Ville et le Commerce ; hausse d'environ 1 point par an depuis 2010. | I46: S20 | J46: Banque des Territoires, d'après l'Institut pour la Ville et le Commerce, Vacance commerciale : les remèdes de l'Institut pour la Ville et le Commerce | K46: s.d. | L46: Presse / média spécialisé | M46: C - Via un relais (presse, synthèse, autre rapport) | N46: https://www.banquedesterritoires.fr/vacance-commerciale-les-remedes-de-linstitut-pour-la-ville-et-le-commerce | O46: Seconde vérification (01/10/2026) : relu dans l'article (relais de l'IVC).
A47: 43 | B47: 3. Centres-villes : vacance commerciale | C47: Taux de vacance en centre-ville, villes de 50 000 à 100 000 habitants | D47: 10.8 | E47: % | F47: 2024 | G47: Villes de 50 000 à 100 000 habitants | H47: 10,6 % en 2019. Panel Codata : 155 000 emplacements dans les centres-villes de 355 communes. | I47: S21 | J47: Banque des Territoires (Localtis), d'après une étude de la FACT (01/12/2025), La progression de la vacance commerciale ralentit, surtout dans les villes moyennes | K47: 02/12/2025 | L47: Presse / média spécialisé | M47: C - Via un relais (presse, synthèse, autre rapport) | N47: https://www.banquedesterritoires.fr/la-progression-de-la-vacance-commerciale-ralentit-surtout-dans-les-villes-moyennes | O47: Seconde vérification (01/10/2026) : relu dans l'article. Les chiffres d'une version antérieure de cette page (métropoles, villes moyennes, petites villes) ont été retirés car introuvables.
A48: 44 | B48: 3. Centres-villes : vacance commerciale | C48: Part des villes ayant réduit leur vacance commerciale en centre-ville | D48: 37 | E48: % | F48: 2019-2024 | G48: 355 communes suivies par Codata | H48: 12 % entre 2014 et 2019. 48 % parmi les villes de 50 000 à 100 000 habitants. | I48: S21 | J48: Banque des Territoires (Localtis), d'après une étude de la FACT (01/12/2025), La progression de la vacance commerciale ralentit, surtout dans les villes moyennes | K48: 02/12/2025 | L48: Presse / média spécialisé | M48: C - Via un relais (presse, synthèse, autre rapport) | N48: https://www.banquedesterritoires.fr/la-progression-de-la-vacance-commerciale-ralentit-surtout-dans-les-villes-moyennes | O48: Seconde vérification (01/10/2026) : relu dans l'article.
A49: 45 | B49: 3. Centres-villes : vacance commerciale | C49: Taux de vacance moyen en centre-ville, villes de plus de 100 000 habitants | D49: 8.7 | E49: % | F49: 2024 | G49: Villes de plus de 100 000 habitants | H49: Contre 11 % pour l'ensemble des villes analysées ; hausse accélérée depuis 2019. | I49: S21 | J49: Banque des Territoires (Localtis), d'après une étude de la FACT (01/12/2025), La progression de la vacance commerciale ralentit, surtout dans les villes moyennes | K49: 02/12/2025 | L49: Presse / média spécialisé | M49: C - Via un relais (presse, synthèse, autre rapport) | N49: https://www.banquedesterritoires.fr/la-progression-de-la-vacance-commerciale-ralentit-surtout-dans-les-villes-moyennes | O49: Seconde vérification (01/10/2026) : relu dans l'article.
A50: 46 | B50: 3. Centres-villes : vacance commerciale | C50: Hausse de la vacance en centre-ville hors Île-de-France | D50: 1 | E50: point | F50: 2019-2024 | G50: France hors Île-de-France | H50: +3,2 points entre 2014 et 2019. En Île-de-France : +2,6 contre +1,5. | I50: S21 | J50: Banque des Territoires (Localtis), d'après une étude de la FACT (01/12/2025), La progression de la vacance commerciale ralentit, surtout dans les villes moyennes | K50: 02/12/2025 | L50: Presse / média spécialisé | M50: C - Via un relais (presse, synthèse, autre rapport) | N50: https://www.banquedesterritoires.fr/la-progression-de-la-vacance-commerciale-ralentit-surtout-dans-les-villes-moyennes | O50: Seconde vérification (01/10/2026) : relu. Selon l'étude, ni la démographie, ni l'offre touristique, ni la présence d'enseignes nationales n'expliquent ces évolutions.
A51: 47 | B51: 3. Centres-villes : vacance commerciale | C51: Taux de vacance dans les centres-villes Action Cœur de Ville | D51: 13 | E51: % | F51: 2020 | G51: Villes ACV | H51: 13 % en 2020, en hausse de 1 % par rapport à 2019 (données ANCT). | I51: S22 | J51: Sénat, mission conjointe de contrôle, Revitalisation des centres-villes et des centres-bourgs : entre enthousiasme et frustrations, rapport d'information n° 910 (2021-2022) | K51: 2022 | L51: Rapport institutionnel (Cour des comptes, Parlement, inspections, mission) | M51: A - Relu dans la source primaire | N51: https://www.senat.fr/rap/r21-910/r21-9109.html | O51: Seconde vérification (01/10/2026) : relu dans le rapport.
A52: 48 | B52: 3. Centres-villes : vacance commerciale | C52: Taux de vacance commerciale tous sites | D52: 10.64 | E52: % | F52: 2024 | G52: France | H52: Codata Digest France (janvier 2025) : rues marchandes, centres commerciaux et zones commerciales. 9,73 % en 2023. | I52: S09 | J52: Procos, Dossier de presse, conférence annuelle | K52: 12/02/2025 | L52: Fédération ou cabinet privé | M52: A - Relu dans la source primaire | N52: https://www.procos.org/images/procos/presse/2025/Conf_0225/procos_dp_120225_site.pdf | O52: La mission de 2025 (S27) attribue 10,64 % aux seuls centres-villes.
A53: 49 | B53: 3. Centres-villes : vacance commerciale | C53: Taux de vacance dans les rues marchandes (pied d'immeuble) | D53: 10.85 | E53: % | F53: 2024 | G53: France | H53: Codata ; 9,73 % en 2023. | I53: S09 | J53: Procos, Dossier de presse, conférence annuelle | K53: 12/02/2025 | L53: Fédération ou cabinet privé | M53: A - Relu dans la source primaire | N53: https://www.procos.org/images/procos/presse/2025/Conf_0225/procos_dp_120225_site.pdf | O53: Panel de 4 045 sites selon L'Échommerces (S15).
A54: 50 | B54: 3. Centres-villes : vacance commerciale | C54: Taux de vacance en pied d'immeuble de centre-ville | D54: 11.7 | E54: % | F54: 2025 | G54: France | H54: Codata Digest 2026 ; 10,8 % en 2024. | I54: S14 | J54: Codata, Codata Digest 2026 (relayé par L'Échommerces) | K54: 2026 | L54: Fédération ou cabinet privé | M54: E - Repris de la présentation OCDE (non revérifié) | O54: Seconde vérification (01/10/2026) : le lien précédemment associé renvoyait à un article de 2025 ; publication d'origine à retrouver.
A55: 51 | B55: 3. Centres-villes : vacance commerciale | C55: Taux de vacance commerciale en centre-ville | D55: 11 | E55: % | F55: 2022 (chiffres Procos) | G55: France | H55: Valeur donnée « par exemple » pour comparer avec les zones commerciales (9 %). | I55: S08 | J55: Gouvernement (ministères Économie, Transition écologique, Cohésion des territoires), Un nouvel horizon pour les zones commerciales, dossier de presse | K55: 09/2023 | L55: Administration / opérateur public | M55: A - Relu dans la source primaire | N55: https://www.info.gouv.fr/upload/media/content/0001/07/2dc90efc2c1a0e97572bf027240fac63e4dc9d75.pdf
A56: 52 | B56: 3. Centres-villes : vacance commerciale | C56: Taux de vacance commerciale national | D56: 14 | E56: % | F56: 2024 | G56: France | H56: « La vacance commerciale a doublé en dix ans, atteignant 14 % en 2024 » ; champ non précisé. | I56: S28 | J56: Direction générale des Entreprises, Mission sur l'avenir du commerce de proximité : neuf mesures retenues | K56: 11/2025 | L56: Administration / opérateur public | M56: A - Relu dans la source primaire | N56: https://www.entreprises.gouv.fr/la-dge/actualites/mission-sur-lavenir-du-commerce-de-proximite-neuf-mesures-retenues-pour | O56: Seconde vérification (01/10/2026) : chiffre du communiqué de la DGE ; il ne figure pas tel quel dans le rapport de la mission.
A57: 53 | B57: 3. Centres-villes : vacance commerciale | C57: Taux de vacance commerciale dans les centres-villes | D57: 10.64 | E57: % | F57: 2024 | G57: Centres-villes | H57: 9,73 % en 2023 ; plus de 16 % dans les galeries marchandes. | I57: S27 | J57: Mission sur l'avenir du commerce de proximité (rapport remis au Gouvernement), Rapport sur l'avenir du commerce de proximité dans les centres-villes et les QPV | K57: 05/11/2025 | L57: Rapport institutionnel (Cour des comptes, Parlement, inspections, mission) | M57: A - Relu dans la source primaire | N57: https://www.banquedesterritoires.fr/sites/default/files/2025-11/Rapport-mission-commerce-de-proximite-centres-villes-QPVf.pdf | O57: Seconde vérification (01/10/2026) : relu dans le rapport de la mission.
A58: 54 | B58: 3. Centres-villes : vacance commerciale | C58: Part des boutiques fermées en centre-ville | D58: 1 sur 10 | E58: ratio | F58: 2025 | G58: France | H58: Formulation du communiqué de la DGE sur la mission. | I58: S28 | J58: Direction générale des Entreprises, Mission sur l'avenir du commerce de proximité : neuf mesures retenues | K58: 11/2025 | L58: Administration / opérateur public | M58: D - Non vérifié : origine à confirmer | N58: https://www.entreprises.gouv.fr/la-dge/actualites/mission-sur-lavenir-du-commerce-de-proximite-neuf-mesures-retenues-pour | O58: Seconde vérification (01/10/2026) : formule non retrouvée dans le communiqué de la DGE ni dans le rapport de la mission.
A59: 55 | B59: 3. Centres-villes : vacance commerciale | C59: Taux de vacance dans les villes Action Cœur de Ville | D59: 13.4 | E59: % | F59: 2023 | G59: Villes ACV | H59: Baromètre Codata / FACT 2024 : 13,4 % en 2023 contre 12,5 % en 2022 ; hors ACV, 7,7 % en 2023 contre 7,4 % en 2022. | I59: S17 | J59: Points de Vente, d'après le baromètre Codata / FACT, La hausse de la vacance commerciale reprend dans les centres-villes | K59: 23/05/2024 | L59: Presse / média spécialisé | M59: C - Via un relais (presse, synthèse, autre rapport) | N59: https://pointsdevente.fr/fil-info/2024-05-23-la-hausse-de-la-vacance-commerciale-reprend-dans-les-centres-villes/ | O59: Seconde vérification (01/10/2026) : année corrigée (2023 et non 2024), relu dans l'article.
A60: 56 | B60: 3. Centres-villes : vacance commerciale | C60: Taux de vacance commerciale moyen, toutes communes | D60: 9.67 | E60: % | F60: 2024 | G60: France | H60: Baromètre Codata / FACT ; 9,22 % en 2022. | I60: S17 | J60: Points de Vente, d'après le baromètre Codata / FACT, La hausse de la vacance commerciale reprend dans les centres-villes | K60: 23/05/2024 | L60: Presse / média spécialisé | M60: D - Non vérifié : origine à confirmer | N60: https://pointsdevente.fr/fil-info/2024-05-23-la-hausse-de-la-vacance-commerciale-reprend-dans-les-centres-villes/ | O60: Seconde vérification (01/10/2026) : chiffre non retrouvé dans l'article cité.
A61: 57 | B61: 3. Centres-villes : vacance commerciale | C61: Taux de vacance dans les villes Action Cœur de Ville | D61: 12.5 | E61: % | F61: 2022 | G61: Villes ACV | H61: Étude Codata / FACT : pic à 14,5 % en 2020 (7,6 % hors ACV), puis 12,5 % en 2022 contre 7,39 % hors ACV ; baisse de 1,7 point depuis 2020 (−0,3 point hors ACV). | I61: S16 | J61: Codata, Quel bilan tirer du plan ACV sur la vacance commerciale des centres-villes de villes moyennes ? (étude Codata / FACT) | K61: s.d. (données 2018-2022) | L61: Fédération ou cabinet privé | M61: C - Via un relais (presse, synthèse, autre rapport) | N61: https://www.codata.eu/blog/quel-bilan-tirer-du-plan-acv-sur-la-vacance-commerciale-des-centres-villes-de-villes-moyennes/ | O61: Seconde vérification (01/10/2026) : relu. L'étude n'observe « pas ou peu de relation » entre vacance, dynamique démographique et revenu.
A62: 58 | B62: 3. Centres-villes : vacance commerciale | C62: Taux de vacance à Vierzon | D62: 28.8 | E62: % | F62: 2018 | G62: Vierzon (centre-ville) | H62: 22,2 % en 2022. | I62: S16 | J62: Codata, Quel bilan tirer du plan ACV sur la vacance commerciale des centres-villes de villes moyennes ? (étude Codata / FACT) | K62: s.d. (données 2018-2022) | L62: Fédération ou cabinet privé | M62: C - Via un relais (presse, synthèse, autre rapport) | N62: https://www.codata.eu/blog/quel-bilan-tirer-du-plan-acv-sur-la-vacance-commerciale-des-centres-villes-de-villes-moyennes/ | O62: Seconde vérification (01/10/2026) : relu dans l'article.
A63: 59 | B63: 3. Centres-villes : vacance commerciale | C63: Taux de vacance à Calais | D63: 21.7 | E63: % | F63: 2018 | G63: Calais (centre-ville) | H63: 14 % en 2022 (−7,7 points). | I63: S16 | J63: Codata, Quel bilan tirer du plan ACV sur la vacance commerciale des centres-villes de villes moyennes ? (étude Codata / FACT) | K63: s.d. (données 2018-2022) | L63: Fédération ou cabinet privé | M63: C - Via un relais (presse, synthèse, autre rapport) | N63: https://www.codata.eu/blog/quel-bilan-tirer-du-plan-acv-sur-la-vacance-commerciale-des-centres-villes-de-villes-moyennes/ | O63: Seconde vérification (01/10/2026) : valeur corrigée (21,7 %).
A64: 60 | B64: 3. Centres-villes : vacance commerciale | C64: Taux de vacance à Bagnols-sur-Cèze | D64: 21.3 | E64: % | F64: 2018 | G64: Bagnols-sur-Cèze (centre-ville) | H64: 14,3 % en 2022. | I64: S16 | J64: Codata, Quel bilan tirer du plan ACV sur la vacance commerciale des centres-villes de villes moyennes ? (étude Codata / FACT) | K64: s.d. (données 2018-2022) | L64: Fédération ou cabinet privé | M64: C - Via un relais (presse, synthèse, autre rapport) | N64: https://www.codata.eu/blog/quel-bilan-tirer-du-plan-acv-sur-la-vacance-commerciale-des-centres-villes-de-villes-moyennes/ | O64: Seconde vérification (01/10/2026) : relu dans l'article.
A65: 61 | B65: 3. Centres-villes : vacance commerciale | C65: Taux de vacance par région, le plus élevé (Occitanie) | D65: 12.46 | E65: % | F65: 2024 | G65: Occitanie | H65: Codata. Le plus faible : Bretagne, 8,92 %. | I65: S09 | J65: Procos, Dossier de presse, conférence annuelle | K65: 12/02/2025 | L65: Fédération ou cabinet privé | M65: A - Relu dans la source primaire | N65: https://www.procos.org/images/procos/presse/2025/Conf_0225/procos_dp_120225_site.pdf
A66: 62 | B66: 3. Centres-villes : vacance commerciale | C66: Taux de vacance commerciale en centre-ville (moyenne) | D66: 12.3 | E66: % | F66: 2020 | G66: Centres-villes | H66: Taux de locaux commerciaux inoccupés ; 7 % en 2012. | I66: S23 | J66: Cour des comptes, La politique de l'État en faveur du commerce de proximité, rapport public thématique (période 2017-2022) | K66: 29/09/2023 | L66: Rapport institutionnel (Cour des comptes, Parlement, inspections, mission) | M66: A - Relu dans la source primaire | N66: https://www.ccomptes.fr/sites/default/files/2023-10/20230929-politiques-publiques-commerce-proximite.pdf | O66: Relu dans le rapport (p. 22) ; le panel de mesure n'est pas précisé dans ce passage.
A67: 63 | B67: 3. Centres-villes : vacance commerciale | C67: Villes dont la vacance commerciale dépasse 20 % | D67: 40 | E67: villes (près de) | F67: 2022 | G67: France | H67: 12 villes dépassent 25 %. La vacance « frictionnelle » est estimée à 6 %. Ces villes se situent surtout dans les départements en recul démographique. | I67: S23 | J67: Cour des comptes, La politique de l'État en faveur du commerce de proximité, rapport public thématique (période 2017-2022) | K67: 29/09/2023 | L67: Rapport institutionnel (Cour des comptes, Parlement, inspections, mission) | M67: A - Relu dans la source primaire | N67: https://www.ccomptes.fr/sites/default/files/2023-10/20230929-politiques-publiques-commerce-proximite.pdf | O67: Relu dans le rapport (p. 23).
A68: 64 | B68: 3. Centres-villes : vacance commerciale | C68: Part des communes Action Cœur de Ville dont la vacance s'est dégradée | D68: 40 | E68: % (environ) | F68: 2021-2022 | G68: Communes ACV | H68: Alors que la vacance moyenne des villes ACV baisse plus vite que dans les autres villes moyennes. | I68: S23 | J68: Cour des comptes, La politique de l'État en faveur du commerce de proximité, rapport public thématique (période 2017-2022) | K68: 29/09/2023 | L68: Rapport institutionnel (Cour des comptes, Parlement, inspections, mission) | M68: A - Relu dans la source primaire | N68: https://www.ccomptes.fr/sites/default/files/2023-10/20230929-politiques-publiques-commerce-proximite.pdf | O68: Relu dans le rapport (p. 12, synthèse).
A69: 65 | B69: 3. Centres-villes : vacance commerciale | C69: Taux de vacance commerciale tous formats | D69: 11.6 | E69: % | F69: 2025 | G69: France | H69: 10,7 % en 2024. | I69: S53 | J69: Cour des comptes (RPA 2026, via synthèse), Rapport public annuel 2026 : cohésion territoriale et attractivité des territoires | K69: 2026 | L69: Rapport institutionnel (Cour des comptes, Parlement, inspections, mission) | M69: D - Non vérifié : origine à confirmer | N69: https://www.ccomptes.fr/fr/publications/le-rapport-public-annuel-2026 | O69: Chiffre lu dans une synthèse automatique du RPA 2026 ; à vérifier dans le rapport.
A70: 66 | B70: 4. Fréquentation, consommation, offre | C70: Évolution de la fréquentation des magasins en centre-ville | D70: -1.8 | E70: % sur un an | F70: 2024 vs 2023 | G70: France | H70: Observatoire de la fréquentation Procos / Stackr. | I70: S09 | J70: Procos, Dossier de presse, conférence annuelle | K70: 12/02/2025 | L70: Fédération ou cabinet privé | M70: A - Relu dans la source primaire | N70: https://www.procos.org/images/procos/presse/2025/Conf_0225/procos_dp_120225_site.pdf | O70: Périphérie −1,2 % ; centres commerciaux −0,8 % ; ensemble −1,6 %.
A71: 67 | B71: 4. Fréquentation, consommation, offre | C71: Évolution de la fréquentation des magasins en périphérie | D71: -1.2 | E71: % sur un an | F71: 2024 vs 2023 | G71: France | H71: Idem. | I71: S09 | J71: Procos, Dossier de presse, conférence annuelle | K71: 12/02/2025 | L71: Fédération ou cabinet privé | M71: A - Relu dans la source primaire | N71: https://www.procos.org/images/procos/presse/2025/Conf_0225/procos_dp_120225_site.pdf
A72: 68 | B72: 4. Fréquentation, consommation, offre | C72: Évolution de la fréquentation des magasins, ensemble | D72: -1.6 | E72: % sur un an | F72: 2024 vs 2023 | G72: France | H72: Idem ; −2,3 % en 2023 selon nos notes. | I72: S09 | J72: Procos, Dossier de presse, conférence annuelle | K72: 12/02/2025 | L72: Fédération ou cabinet privé | M72: A - Relu dans la source primaire | N72: https://www.procos.org/images/procos/presse/2025/Conf_0225/procos_dp_120225_site.pdf
A73: 69 | B73: 4. Fréquentation, consommation, offre | C73: Part de marché du commerce de proximité dans l'alimentaire | D73: 17 | E73: % | F73: 2017 | G73: France | H73: 22 % en 1993 ; baisse au bénéfice de la grande distribution. | I73: S23 | J73: Cour des comptes, La politique de l'État en faveur du commerce de proximité, rapport public thématique (période 2017-2022) | K73: 29/09/2023 | L73: Rapport institutionnel (Cour des comptes, Parlement, inspections, mission) | M73: A - Relu dans la source primaire | N73: https://www.ccomptes.fr/sites/default/files/2023-10/20230929-politiques-publiques-commerce-proximite.pdf | O73: Relu dans le rapport (p. 21).
A74: 70 | B74: 4. Fréquentation, consommation, offre | C74: Part de marché du commerce de proximité dans l'alimentaire | D74: 20 | E74: % | F74: 2021 | G74: France | H74: Remontée après 2017 ; les hypermarchés restent le premier lieu d'achat. | I74: S23 | J74: Cour des comptes, La politique de l'État en faveur du commerce de proximité, rapport public thématique (période 2017-2022) | K74: 29/09/2023 | L74: Rapport institutionnel (Cour des comptes, Parlement, inspections, mission) | M74: A - Relu dans la source primaire | N74: https://www.ccomptes.fr/sites/default/files/2023-10/20230929-politiques-publiques-commerce-proximite.pdf | O74: Relu dans le rapport (p. 21).
A75: 71 | B75: 4. Fréquentation, consommation, offre | C75: Part des ventes en ligne dans le commerce de détail | D75: 12.5 | E75: % | F75: 2022 | G75: France | H75: Ventes en ligne de produits et services ; 146,9 milliards d'euros en 2022. | I75: S23 | J75: Cour des comptes, La politique de l'État en faveur du commerce de proximité, rapport public thématique (période 2017-2022) | K75: 29/09/2023 | L75: Rapport institutionnel (Cour des comptes, Parlement, inspections, mission) | M75: A - Relu dans la source primaire | N75: https://www.ccomptes.fr/sites/default/files/2023-10/20230929-politiques-publiques-commerce-proximite.pdf | O75: Relu dans le rapport (p. 56). Champ différent du chiffre Fevad cité par le CAE (14,1 % en 2021).
A76: 72 | B76: 4. Fréquentation, consommation, offre | C76: Part des communes sans aucun commerce de détail | D76: 62 | E76: % | F76: 2021 | G76: France | H76: 53 % en 2010. | I76: S23 | J76: Cour des comptes, La politique de l'État en faveur du commerce de proximité, rapport public thématique (période 2017-2022) | K76: 29/09/2023 | L76: Rapport institutionnel (Cour des comptes, Parlement, inspections, mission) | M76: A - Relu dans la source primaire | N76: https://www.ccomptes.fr/sites/default/files/2023-10/20230929-politiques-publiques-commerce-proximite.pdf | O76: Relu dans le rapport (p. 68), d'après l'Insee.
A77: 73 | B77: 4. Fréquentation, consommation, offre | C77: Population à plus de 7 minutes de trajet motorisé d'une petite surface alimentaire | D77: 9 | E77: % (environ) | F77: non précisée | G77: France | H77: Près de 6 millions de personnes. | I77: S23 | J77: Cour des comptes, La politique de l'État en faveur du commerce de proximité, rapport public thématique (période 2017-2022) | K77: 29/09/2023 | L77: Rapport institutionnel (Cour des comptes, Parlement, inspections, mission) | M77: A - Relu dans la source primaire | N77: https://www.ccomptes.fr/sites/default/files/2023-10/20230929-politiques-publiques-commerce-proximite.pdf | O77: Relu dans le rapport (p. 68), d'après l'Insee.
A78: 74 | B78: 4. Fréquentation, consommation, offre | C78: Population ayant un faible accès au commerce spécialisé | D78: 31 | E78: % | F78: non précisée (études Insee) | G78: Communes en périphérie des moyens et petits pôles | H78: Entre 70 % et 80 % des habitants de ces communes ; habillement, loisirs, culture, sport, alimentation spécialisée. | I78: S23 | J78: Cour des comptes, La politique de l'État en faveur du commerce de proximité, rapport public thématique (période 2017-2022) | K78: 29/09/2023 | L78: Rapport institutionnel (Cour des comptes, Parlement, inspections, mission) | M78: A - Relu dans la source primaire | N78: https://www.ccomptes.fr/sites/default/files/2023-10/20230929-politiques-publiques-commerce-proximite.pdf | O78: Relu dans le rapport (p. 69), d'après l'Insee.
A79: 75 | B79: 4. Fréquentation, consommation, offre | C79: Poids des secteurs fragilisés (avant ou pendant la crise sanitaire) dans l'offre de nombreux centres-villes | D79: 40 à 60 | E79: % | F79: 2020-2021 | G79: Centres-villes | H79: Prêt-à-porter, jouet, culture-loisirs, restaurants, bars, souvenirs, « souvent avec une surreprésentation de TPE et d'indépendants ». | I79: S22 | J79: Sénat, mission conjointe de contrôle, Revitalisation des centres-villes et des centres-bourgs : entre enthousiasme et frustrations, rapport d'information n° 910 (2021-2022) | K79: 2022 | L79: Rapport institutionnel (Cour des comptes, Parlement, inspections, mission) | M79: A - Relu dans la source primaire | N79: https://www.senat.fr/rap/r21-910/r21-9109.html | O79: Seconde vérification (01/10/2026) : intitulé corrigé : le rapport ne parle pas du seul équipement de la personne.
A80: 76 | B80: 4. Fréquentation, consommation, offre | C80: Part de l'habillement dans l'offre en pied d'immeuble | D80: 15.05 | E80: % | F80: 2024 | G80: France | H80: 20,92 % en 2015. Les cafés-hôtels-restaurants montent à 21,67 % de l'offre. | I80: S15 | J80: L'Échommerces, d'après Codata, La vacance commerciale progresse de nouveau en France | K80: 2025 | L80: Presse / média spécialisé | M80: C - Via un relais (presse, synthèse, autre rapport) | N80: https://lechommerces.fr/la-vacance-commerciale-progresse-de-nouveau-en-france/
A81: 77 | B81: 4. Fréquentation, consommation, offre | C81: Établissements perdus par l'équipement de la personne en dix ans | D81: 14000 | E81: établissements | F81: environ 2016-2026 | G81: France | H81: Équipement de la personne. | I81: S11 | J81: Icade et SCET, Baromètre des entrées de ville, 2e édition : cap sur les projets | K81: 09/2026 | L81: Fédération ou cabinet privé | M81: C - Via un relais (presse, synthèse, autre rapport) | N81: https://www.icade.fr/content/download/7372/file/barom%C3%A8tre-entr%C3%A9es-de-ville-2e-edition-cap-sur-projets.pdf | O81: Seconde vérification (01/10/2026) : relu (p. 61 du baromètre), qui cite la revue Urbanisme n° 448, avril 2026.
A82: 78 | B82: 4. Fréquentation, consommation, offre | C82: Part du e-commerce dans le commerce de détail | D82: 14.1 | E82: % | F82: 2021 | G82: France | H82: Estimation Fevad citée par le CAE ; 129 milliards d'euros dépensés en ligne en 2021 (biens et services). | I82: S12 | J82: Allain M.-L. et Epaulard A. (CAE), Petits commerces : déclin ou mutation ?, Les notes du CAE n° 77 | K82: 05/2023 | L82: Recherche académique / CAE | M82: A - Relu dans la source primaire | N82: https://www.cae-eco.fr/
A83: 79 | B83: 5. QPV : commerce et contexte | C83: Nombre de QPV en métropole | D83: 1362 | E83: quartiers | F83: 01/01/2025 | G83: France métropolitaine | H83: Géographie prioritaire actualisée au 1er janvier 2024 en métropole ; 247 quartiers en outre-mer (actualisés au 1er janvier 2025). | I83: S33 | J83: ANCT, Quartiers prioritaires de la politique de la ville | K83: 2025 | L83: Administration / opérateur public | M83: A - Relu dans la source primaire | N83: https://anct.gouv.fr/quartiers-prioritaires
A84: 80 | B84: 5. QPV : commerce et contexte | C84: Population des QPV | D84: 6 | E84: millions d'habitants (plus de) | F84: 2025 | G84: France | I84: S33 | J84: ANCT, Quartiers prioritaires de la politique de la ville | K84: 2025 | L84: Administration / opérateur public | M84: D - Non vérifié : origine à confirmer | N84: https://anct.gouv.fr/quartiers-prioritaires | O84: Seconde vérification (01/10/2026) : non retrouvé sur la page de l'ANCT citée.
A85: 81 | B85: 5. QPV : commerce et contexte | C85: Taux de chômage en QPV | D85: 18.3 | E85: % | F85: 2022 | G85: QPV | H85: 7,5 % dans les unités urbaines englobantes ; 25 % en 2014. | I85: S31 | J85: Observatoire des inégalités, d'après l'ONPV, Le chômage dans les quartiers prioritaires | K85: s.d. (données 2022) | L85: Presse / média spécialisé | M85: C - Via un relais (presse, synthèse, autre rapport) | N85: https://www.inegalites.fr/Chomage-QPV | O85: Moins de 30 ans : 26 % contre 13,5 %. Seconde vérification (01/10/2026) : page non lisible automatiquement ; à recouper avec les publications de l'ONPV ou de l'Insee.
A86: 82 | B86: 5. QPV : commerce et contexte | C86: Taux de pauvreté en QPV | D86: 45 | E86: % | F86: 2021 | G86: QPV | H86: 2,5 fois le taux des villes qui les abritent. | I86: S32 | J86: Observatoire des inégalités, d'après l'Insee, Les revenus et la pauvreté dans les quartiers les plus en difficulté | K86: s.d. (données 2021) | L86: Presse / média spécialisé | M86: C - Via un relais (presse, synthèse, autre rapport) | N86: https://www.inegalites.fr/Les-revenus-et-la-pauvrete-dans-les-quartiers-les-plus-en-difficulte | O86: Seconde vérification (01/10/2026) : page non lisible automatiquement ; à recouper avec les publications de l'ONPV ou de l'Insee.
A87: 83 | B87: 5. QPV : commerce et contexte | C87: Niveau de vie médian en QPV | D87: 1213 | E87: € par mois | F87: 2021 | G87: QPV | H87: 1 900 € dans le reste des agglomérations englobantes. | I87: S32 | J87: Observatoire des inégalités, d'après l'Insee, Les revenus et la pauvreté dans les quartiers les plus en difficulté | K87: s.d. (données 2021) | L87: Presse / média spécialisé | M87: C - Via un relais (presse, synthèse, autre rapport) | N87: https://www.inegalites.fr/Les-revenus-et-la-pauvrete-dans-les-quartiers-les-plus-en-difficulte | O87: Seconde vérification (01/10/2026) : page non lisible automatiquement ; à recouper avec les publications de l'ONPV ou de l'Insee.
A88: 84 | B88: 5. QPV : commerce et contexte | C88: Évolution du nombre d'entreprises en QPV | D88: x 2 (presque) | E88: multiplicateur | F88: 5 ans avant 2023 | G88: QPV | H88: Toutes entreprises ; secteurs les plus représentés : commerce, transport, construction. | I88: S30 | J88: ONPV / ANCT, Comprendre le tissu économique en QPV : une hausse du nombre d'entreprises | K88: 2023 | L88: Statistique publique | M88: A - Relu dans la source primaire | N88: https://www.onpv.fr/uploads/media_items/onpv-dossier-entreprises-2023.original.pdf
A89: 85 | B89: 5. QPV : commerce et contexte | C89: Part du commerce de détail dans les établissements des QPV | D89: 15.8 | E89: % | F89: 01/01/2021 | G89: QPV de métropole | H89: 18,2 % dans les QPV des DROM. | I89: S30 | J89: ONPV / ANCT, Comprendre le tissu économique en QPV : une hausse du nombre d'entreprises | K89: 2023 | L89: Statistique publique | M89: A - Relu dans la source primaire | N89: https://www.onpv.fr/uploads/media_items/onpv-dossier-entreprises-2023.original.pdf
A90: 86 | B90: 5. QPV : commerce et contexte | C90: Part du commerce de détail dans les créations d'établissements en QPV | D90: 9.2 | E90: % | F90: 2021 | G90: QPV de métropole | H90: Sur 92 590 nouveaux établissements. | I90: S30 | J90: ONPV / ANCT, Comprendre le tissu économique en QPV : une hausse du nombre d'entreprises | K90: 2023 | L90: Statistique publique | M90: A - Relu dans la source primaire | N90: https://www.onpv.fr/uploads/media_items/onpv-dossier-entreprises-2023.original.pdf
A91: 87 | B91: 5. QPV : commerce et contexte | C91: Opérations ANRU consacrées au commerce de proximité | D91: 122 | E91: opérations | F91: s.d. (NPNRU) | G91: QPV en renouvellement urbain | H91: Dotation ANRU de 322 M€ et cofinancement de 67 M€. | I91: S34 | J91: ANRU, Le commerce dans les quartiers prioritaires en renouvellement urbain | K91: 2025 | L91: Administration / opérateur public | M91: B - Source primaire consultée pendant la recherche (non relue) | N91: https://www.anru.fr/la-docutheque/le-commerce-dans-les-quartiers-prioritaires-en-renouvellement-urbain
A92: 88 | B92: 5. QPV : commerce et contexte | C92: Centres commerciaux ou pôles artisanaux restructurés par l'EPARECA | D92: 50 | E92: (plus de) | F92: depuis 2001 | G92: QPV | H92: Opérateur public créé en 1996, intégré depuis à l'ANCT. | I92: S46 | J92: EPARECA / LSA Conso ; CGET, L'Epareca aide les quartiers sensibles ; De nouvelles opérations pour le commerce et l'artisanat en QPV | K92: s.d. | L92: Presse / média spécialisé | M92: C - Via un relais (presse, synthèse, autre rapport) | N92: https://www.lsa-conso.fr/l-epareca-aide-les-quartiers-sensibles,34533
A93: 89 | B93: 5. QPV : commerce et contexte | C93: Coût d'une restructuration de centre commercial en QPV (Le Mans) | D93: 4212100 | E93: € | F93: 2023-2025 | G93: Le Mans | H93: Financement : Le Mans Métropole 1 254 750 €, ANCT 1 203 491 €, ANRU 1 058 131 €, FRLA 695 728 €. | I93: S47 | J93: ANCT, Dossier de presse, restructuration d'un centre commercial en QPV au Mans | K93: 10/2024 | L93: Administration / opérateur public | M93: A - Relu dans la source primaire | N93: https://media.anct.gouv.fr/s3fs-public/2024-10/DP_ANCT_LE%20MANS_2024_v4%20(7).pdf
A94: 90 | B94: 6. Autorisations CDAC / CNAC | C94: Surface de vente autorisée par les CDAC | D94: 583466 | E94: m² | F94: 2020 | G94: France | H94: Autorisations et avis favorables des CDAC (tableau 1). | I94: S10 | J94: CNAC / Direction générale des Entreprises, Rapport d'activité 2024 de la Commission nationale d'aménagement commercial | K94: 2025 | L94: Administration / opérateur public | M94: A - Relu dans la source primaire | N94: https://www.entreprises.gouv.fr/files/files/Publications/2025/rapports-activite/ra-cnac-2024.pdf
A95: 91 | B95: 6. Autorisations CDAC / CNAC | C95: Surface de vente autorisée par les CDAC | D95: 688220 | E95: m² | F95: 2021 | G95: France | H95: Idem. | I95: S10 | J95: CNAC / Direction générale des Entreprises, Rapport d'activité 2024 de la Commission nationale d'aménagement commercial | K95: 2025 | L95: Administration / opérateur public | M95: A - Relu dans la source primaire | N95: https://www.entreprises.gouv.fr/files/files/Publications/2025/rapports-activite/ra-cnac-2024.pdf
A96: 92 | B96: 6. Autorisations CDAC / CNAC | C96: Surface de vente autorisée par les CDAC | D96: 765384 | E96: m² | F96: 2022 | G96: France | H96: Idem. | I96: S10 | J96: CNAC / Direction générale des Entreprises, Rapport d'activité 2024 de la Commission nationale d'aménagement commercial | K96: 2025 | L96: Administration / opérateur public | M96: A - Relu dans la source primaire | N96: https://www.entreprises.gouv.fr/files/files/Publications/2025/rapports-activite/ra-cnac-2024.pdf
A97: 93 | B97: 6. Autorisations CDAC / CNAC | C97: Surface de vente autorisée par les CDAC | D97: 625386 | E97: m² | F97: 2023 | G97: France | H97: Idem. | I97: S10 | J97: CNAC / Direction générale des Entreprises, Rapport d'activité 2024 de la Commission nationale d'aménagement commercial | K97: 2025 | L97: Administration / opérateur public | M97: A - Relu dans la source primaire | N97: https://www.entreprises.gouv.fr/files/files/Publications/2025/rapports-activite/ra-cnac-2024.pdf
A98: 94 | B98: 6. Autorisations CDAC / CNAC | C98: Surface de vente autorisée par les CDAC | D98: 605844 | E98: m² | F98: 2024 | G98: France | H98: Idem ; 338 autorisations, taux d'autorisation 88 %. | I98: S10 | J98: CNAC / Direction générale des Entreprises, Rapport d'activité 2024 de la Commission nationale d'aménagement commercial | K98: 2025 | L98: Administration / opérateur public | M98: A - Relu dans la source primaire | N98: https://www.entreprises.gouv.fr/files/files/Publications/2025/rapports-activite/ra-cnac-2024.pdf
A99: 95 | B99: 6. Autorisations CDAC / CNAC | C99: Surface de vente examinée par les CDAC | D99: 685215 | E99: m² | F99: 2024 | G99: France | H99: Autorisations + refus (384 dossiers) ; 878 373 m² en 2022. | I99: S10 | J99: CNAC / Direction générale des Entreprises, Rapport d'activité 2024 de la Commission nationale d'aménagement commercial | K99: 2025 | L99: Administration / opérateur public | M99: A - Relu dans la source primaire | N99: https://www.entreprises.gouv.fr/files/files/Publications/2025/rapports-activite/ra-cnac-2024.pdf
A100: 96 | B100: 6. Autorisations CDAC / CNAC | C100: Surface de vente examinée par la CNAC | D100: 234940 | E100: m² | F100: 2024 | G100: France | H100: 487 999 m² en 2023 (−52 %) ; 145 avis ou décisions contre 181. | I100: S10 | J100: CNAC / Direction générale des Entreprises, Rapport d'activité 2024 de la Commission nationale d'aménagement commercial | K100: 2025 | L100: Administration / opérateur public | M100: A - Relu dans la source primaire | N100: https://www.entreprises.gouv.fr/files/files/Publications/2025/rapports-activite/ra-cnac-2024.pdf | O100: Surface moyenne examinée : 1 620 m² (2 696 m² en 2023).
A101: 97 | B101: 6. Autorisations CDAC / CNAC | C101: Surface de vente autorisée par la CNAC | D101: 138031 | E101: m² | F101: 2024 | G101: France | H101: 318 032 m² en 2023 (tableau 2). | I101: S10 | J101: CNAC / Direction générale des Entreprises, Rapport d'activité 2024 de la Commission nationale d'aménagement commercial | K101: 2025 | L101: Administration / opérateur public | M101: A - Relu dans la source primaire | N101: https://www.entreprises.gouv.fr/files/files/Publications/2025/rapports-activite/ra-cnac-2024.pdf
...

Sheet Sources
A1: Sources
A2: Le nombre de chiffres est calculé à partir de l'onglet « Chiffres » (0 = source utilisée seulement pour l'analyse qualitative).
A4: Réf. | B4: Auteur / organisme | C4: Titre | D4: Date de publication | E4: Type de source | F4: Lien | G4: Nb de chiffres dans l'onglet « Chiffres »
A5: S01 | B5: Cerema | C5: Accompagner la mutation des zones commerciales de périphérie | D5: 19/05/2025 | E5: Administration / opérateur public | F5: https://www.cerema.fr/fr/actualites/accompagner-mutation-zones-commerciales-peripherie | G5: =COUNTIF(Chiffres!$I$5:$I$468,A5) -> 4
A6: S02 | B6: Cerema | C6: Les données de géolocalisation des 1500 zones commerciales de périphérie sont en open data (base EmpCom) | D6: 23/01/2024 | E6: Administration / opérateur public | F6: https://www.cerema.fr/fr/actualites/donnees-geolocalisation-1500-zones-commerciales-peripherie | G6: =COUNTIF(Chiffres!$I$5:$I$468,A6) -> 1
A7: S03 | B7: Cerema | C7: Zones commerciales et centres-villes : trouver le bon équilibre | D7: s.d. (vers 2020-2021) | E7: Administration / opérateur public | F7: https://www.cerema.fr/fr/actualites/zones-commerciales-centres-villes-trouver-bon-equilibre | G7: =COUNTIF(Chiffres!$I$5:$I$468,A7) -> 3
A8: S04 | B8: Cerema | C8: Déterminer le potentiel de réindustrialisation des friches dans les zones commerciales | D8: 28/11/2024 | E8: Administration / opérateur public | F8: https://www.cerema.fr/fr/actualites/potentiel-reindustrialisation-friches | G8: =COUNTIF(Chiffres!$I$5:$I$468,A8) -> 1
A9: S05 | B9: Bédué M. et Cohen C. (Insee) | C9: Le commerce de proximité : des pôles plus florissants en périphérie qu'en centre-ville, Insee Première n° 1858 | D9: 20/05/2021 | E9: Statistique publique | F9: https://www.insee.fr/fr/statistiques/5386414 | G9: =COUNTIF(Chiffres!$I$5:$I$468,A9) -> 10
A10: S06 | B10: Cazaubiel A. et Guymarc G. (Insee) | C10: Commerce de proximité dans les villes de taille intermédiaire, Insee Première n° 1782 | D10: 14/11/2019 | E10: Statistique publique | F10: https://www.insee.fr/fr/statistiques/4248184 | G10: =COUNTIF(Chiffres!$I$5:$I$468,A10) -> 4
A11: S07 | B11: Bloch K. et Pichavant A.-S. (Insee) | C11: Entre 2016 et 2022, l'emploi salarié des points de vente progresse davantage en dehors des centres-villes, Insee Première n° 2091 | D11: 27/01/2026 | E11: Statistique publique | F11: https://www.insee.fr/fr/statistiques/8730497 | G11: =COUNTIF(Chiffres!$I$5:$I$468,A11) -> 8
A12: S08 | B12: Gouvernement (ministères Économie, Transition écologique, Cohésion des territoires) | C12: Un nouvel horizon pour les zones commerciales, dossier de presse | D12: 09/2023 | E12: Administration / opérateur public | F12: https://www.info.gouv.fr/upload/media/content/0001/07/2dc90efc2c1a0e97572bf027240fac63e4dc9d75.pdf | G12: =COUNTIF(Chiffres!$I$5:$I$468,A12) -> 4
A13: S09 | B13: Procos | C13: Dossier de presse, conférence annuelle | D13: 12/02/2025 | E13: Fédération ou cabinet privé | F13: https://www.procos.org/images/procos/presse/2025/Conf_0225/procos_dp_120225_site.pdf | G13: =COUNTIF(Chiffres!$I$5:$I$468,A13) -> 15
A14: S10 | B14: CNAC / Direction générale des Entreprises | C14: Rapport d'activité 2024 de la Commission nationale d'aménagement commercial | D14: 2025 | E14: Administration / opérateur public | F14: https://www.entreprises.gouv.fr/files/files/Publications/2025/rapports-activite/ra-cnac-2024.pdf | G14: =COUNTIF(Chiffres!$I$5:$I$468,A14) -> 12
A15: S11 | B15: Icade et SCET | C15: Baromètre des entrées de ville, 2e édition : cap sur les projets | D15: 09/2026 | E15: Fédération ou cabinet privé | F15: https://www.icade.fr/content/download/7372/file/barom%C3%A8tre-entr%C3%A9es-de-ville-2e-edition-cap-sur-projets.pdf | G15: =COUNTIF(Chiffres!$I$5:$I$468,A15) -> 12
A16: S12 | B16: Allain M.-L. et Epaulard A. (CAE) | C16: Petits commerces : déclin ou mutation ?, Les notes du CAE n° 77 | D16: 05/2023 | E16: Recherche académique / CAE | F16: https://www.cae-eco.fr/ | G16: =COUNTIF(Chiffres!$I$5:$I$468,A16) -> 4
A17: S13 | B17: Rexecode | C17: Répartition des ventes du commerce de détail par lieu de vente, d'après Insee, Procos et Fevad | D17: 2024 | E17: Fédération ou cabinet privé | G17: =COUNTIF(Chiffres!$I$5:$I$468,A17) -> 3
A18: S14 | B18: Codata | C18: Codata Digest 2026 (relayé par L'Échommerces) | D18: 2026 | E18: Fédération ou cabinet privé | G18: =COUNTIF(Chiffres!$I$5:$I$468,A18) -> 2
A19: S15 | B19: L'Échommerces, d'après Codata | C19: La vacance commerciale progresse de nouveau en France | D19: 2025 | E19: Presse / média spécialisé | F19: https://lechommerces.fr/la-vacance-commerciale-progresse-de-nouveau-en-france/ | G19: =COUNTIF(Chiffres!$I$5:$I$468,A19) -> 1
A20: S16 | B20: Codata | C20: Quel bilan tirer du plan ACV sur la vacance commerciale des centres-villes de villes moyennes ? (étude Codata / FACT) | D20: s.d. (données 2018-2022) | E20: Fédération ou cabinet privé | F20: https://www.codata.eu/blog/quel-bilan-tirer-du-plan-acv-sur-la-vacance-commerciale-des-centres-villes-de-villes-moyennes/ | G20: =COUNTIF(Chiffres!$I$5:$I$468,A20) -> 4
A21: S17 | B21: Points de Vente, d'après le baromètre Codata / FACT | C21: La hausse de la vacance commerciale reprend dans les centres-villes | D21: 23/05/2024 | E21: Presse / média spécialisé | F21: https://pointsdevente.fr/fil-info/2024-05-23-la-hausse-de-la-vacance-commerciale-reprend-dans-les-centres-villes/ | G21: =COUNTIF(Chiffres!$I$5:$I$468,A21) -> 2
A22: S18 | B22: Public Sénat, citant un rapport du CGEDD (2016) | C22: Revitalisation des centres-villes : un rapport du Sénat pointe un sous-financement | D22: 2022 | E22: Presse / média spécialisé | F22: https://www.publicsenat.fr/actualites/territoires/revitalisation-des-centres-villes-un-rapport-du-senat-pointe-un-sous | G22: =COUNTIF(Chiffres!$I$5:$I$468,A22) -> 2
A23: S19 | B23: CGEDD et IGF (cité par le Cerema) | C23: Rapport interministériel sur la revitalisation commerciale des centres-villes | D23: 2016 | E23: Rapport institutionnel (Cour des comptes, Parlement, inspections, mission) | F23: https://www.cerema.fr/fr/actualites/zones-commerciales-centres-villes-trouver-bon-equilibre | G23: =COUNTIF(Chiffres!$I$5:$I$468,A23) -> 1
A24: S20 | B24: Banque des Territoires, d'après l'Institut pour la Ville et le Commerce | C24: Vacance commerciale : les remèdes de l'Institut pour la Ville et le Commerce | D24: s.d. | E24: Presse / média spécialisé | F24: https://www.banquedesterritoires.fr/vacance-commerciale-les-remedes-de-linstitut-pour-la-ville-et-le-commerce | G24: =COUNTIF(Chiffres!$I$5:$I$468,A24) -> 1
A25: S21 | B25: Banque des Territoires (Localtis), d'après une étude de la FACT (01/12/2025) | C25: La progression de la vacance commerciale ralentit, surtout dans les villes moyennes | D25: 02/12/2025 | E25: Presse / média spécialisé | F25: https://www.banquedesterritoires.fr/la-progression-de-la-vacance-commerciale-ralentit-surtout-dans-les-villes-moyennes | G25: =COUNTIF(Chiffres!$I$5:$I$468,A25) -> 4
A26: S22 | B26: Sénat, mission conjointe de contrôle | C26: Revitalisation des centres-villes et des centres-bourgs : entre enthousiasme et frustrations, rapport d'information n° 910 (2021-2022) | D26: 2022 | E26: Rapport institutionnel (Cour des comptes, Parlement, inspections, mission) | F26: https://www.senat.fr/rap/r21-910/r21-9109.html | G26: =COUNTIF(Chiffres!$I$5:$I$468,A26) -> 5
A27: S23 | B27: Cour des comptes | C27: La politique de l'État en faveur du commerce de proximité, rapport public thématique (période 2017-2022) | D27: 29/09/2023 | E27: Rapport institutionnel (Cour des comptes, Parlement, inspections, mission) | F27: https://www.ccomptes.fr/sites/default/files/2023-10/20230929-politiques-publiques-commerce-proximite.pdf | G27: =COUNTIF(Chiffres!$I$5:$I$468,A27) -> 19
A28: S24 | B28: Cour des comptes | C28: Rapport public annuel 2016, tome 2 : la politique de la ville | D28: 2016 | E28: Rapport institutionnel (Cour des comptes, Parlement, inspections, mission) | F28: https://www.ccomptes.fr/sites/default/files/EzPublish/07-politique-de-la-ville-RPA2016-Tome-2.pdf | G28: =COUNTIF(Chiffres!$I$5:$I$468,A28) -> 0
A29: S25 | B29: Cour des comptes | C29: L'évaluation de l'attractivité des quartiers prioritaires (rapport public thématique) | D29: à préciser | E29: Rapport institutionnel (Cour des comptes, Parlement, inspections, mission) | F29: https://www.ccomptes.fr/fr/publications/levaluation-de-lattractivite-des-quartiers-prioritaires | G29: =COUNTIF(Chiffres!$I$5:$I$468,A29) -> 0
A30: S26 | B30: Cour des comptes (via AEF info, Journal des Arts, Courrier des maires) | C30: Action Cœur de Ville : rapport sur la première phase du programme | D30: 09/2022 | E30: Rapport institutionnel (Cour des comptes, Parlement, inspections, mission) | F30: https://www.aefinfo.fr/depeche/679781-action-coeur-de-ville-un-programme-ambitieux-mais-difficile-a-evaluer-selon-la-cour-des-comptes | G30: =COUNTIF(Chiffres!$I$5:$I$468,A30) -> 2
... A53: S49 | B53: IGF et IGEDD | C53: La revitalisation commerciale des centres-villes | D53: s.d. | E53: Rapport institutionnel (Cour des comptes, Parlement, inspections, mission) | F53: https://www.igf.finances.gouv.fr/igf/accueil/nos-activites/rapports-de-missions/liste-de-tous-les-rapports-de-mi/la-revitalisation-commerciale-de.html | G53: =COUNTIF(Chiffres!$I$5:$I$468,A53) -> 0
A54: S50 | B54: Bertrand M. et Kramarz F. | C54: Does Entry Regulation Hinder Job Creation? Evidence from the French Retail Industry, Quarterly Journal of Economics, 117(4) | D54: 2002 | E54: Recherche académique / CAE | G54: =COUNTIF(Chiffres!$I$5:$I$468,A54) -> 0
A55: S51 | B55: Sadun R. | C55: Does Planning Regulation Protect Independent Retailers?, Review of Economics and Statistics, 97(5) | D55: 2015 | E55: Recherche académique / CAE | G55: =COUNTIF(Chiffres!$I$5:$I$468,A55) -> 0
A56: S52 | B56: Quantin S. et Turner L. (Insee) | C56: Le développement des grandes surfaces et son impact sur la durée de vie du petit commerce alimentaire de proximité, Journées de méthodologie statistique | D56: 2015 | E56: Statistique publique | G56: =COUNTIF(Chiffres!$I$5:$I$468,A56) -> 0
A57: S53 | B57: Cour des comptes (RPA 2026, via synthèse) | C57: Rapport public annuel 2026 : cohésion territoriale et attractivité des territoires | D57: 2026 | E57: Rapport institutionnel (Cour des comptes, Parlement, inspections, mission) | F57: https://www.ccomptes.fr/fr/publications/le-rapport-public-annuel-2026 | G57: =COUNTIF(Chiffres!$I$5:$I$468,A57) -> 1

Sheet Données manquantes
A1: Données et sources manquantes pour une évaluation complète
A2: Ce qu'il faudrait pour mesurer l'influence propre des zones périphériques sur les centres-villes et les QPV, et non une simple corrélation.
A4: N° | B4: Catégorie | C4: Besoin d'évaluation | D4: Donnée ou document manquant | E4: Producteur / détenteur | F4: Ce que cela permettrait de mesurer | G4: Conditions d'accès | H4: Statut dans nos travaux | I4: Priorité | J4: Démarche suggérée
A5: 1 | B5: Données statistiques | C5: Mesurer l'offre en surfaces, pas seulement en nombre d'établissements | D5: Surfaces de vente par établissement (fichier de la taxe sur les surfaces commerciales, TASCOM) | E5: DGFiP ; DGE | F5: Pondérer chaque commerce par sa surface ; suivre l'ouverture des grandes surfaces dans le temps | G5: Non ouvert : demande à la DGFiP ou à la DGE | H5: Manquant | I5: Haute | J5: Demander à la DGE (bureau du commerce) l'accès à une extraction anonymisée par commune
A6: 2 | B6: Données statistiques | C6: Identifier les ouvertures de surfaces en périphérie projet par projet | D6: Base consolidée des décisions CDAC / CNAC (date, adresse, surface, enseigne, autorisation ou refus) | E6: DGE (secrétariat de la CNAC) ; préfectures | F6: Comparer les territoires où un projet a été autorisé et ceux où il a été refusé (approche quasi expérimentale) | G6: Décisions publiées une à une ; pas de base ouverte consolidée | H6: Manquant | I6: Haute | J6: Demander la base nationale à la DGE ; à défaut, Kyris / Procos (payant)
A7: 3 | B7: Données statistiques | C7: Mesurer la vacance commerciale au niveau local | D7: Locaux d'activité vacants (fichiers fonciers, base LOCOMVAC du Cerema) ; relevés de terrain Codata | E7: Cerema (fichiers fonciers) ; Codata (privé) | F7: Mesurer directement la vacance en centre-ville et en QPV, au lieu du nombre d'établissements | G7: Fichiers fonciers : convention réservée aux acteurs publics et chercheurs ; Codata : payant | H7: Manquant | I7: Haute | J7: Demander l'accès aux fichiers fonciers via le Cerema (DataFoncier) ; outil de diagnostic de la vacance annoncé par la mission de 2025
A8: 4 | B8: Données statistiques | C8: Mesurer l'activité réelle (chiffre d'affaires, dépenses) | D8: Dépenses par carte bancaire localisées (lieu d'achat et lieu de résidence) | E8: Groupements bancaires (CB, Crédit Mutuel Alliance Fédérale…) ; Insee en partenariat | F8: Savoir où consomment les habitants des centres et des QPV, et ce que la périphérie capte | G8: Accès par partenariat de recherche | H8: Manquant | I8: Haute | J8: S'inspirer de l'Insee Première n° 2075 (achats frontaliers) qui utilise ces données
A9: 5 | B9: Données statistiques | C9: Mesurer l'emploi salarié par établissement | D9: Base tous salariés / DSN ; FLORES | E9: Insee | F9: Remplacer le critère employeur oui/non par les effectifs ; reproduire les pôles de l'Insee | G9: Accès sécurisé (CASD) sur projet | H9: Partiel (Sirene donne seulement le caractère employeur) | I9: Moyenne | J9: Déposer une demande CASD, ou demander des tableaux à façon à l'Insee
A10: 6 | B10: Données statistiques | C10: Disposer de la géographie des pôles commerciaux de l'Insee | D10: Pôles du commerce de proximité (Insee Première n° 1858 et 2091) | E10: Insee | F10: Comparer directement nos zones (Cerema) avec les pôles de périphérie et de centre-ville de l'Insee | G10: Fichiers de données des publications partiellement en ligne ; contours non publiés | H10: Manquant | I10: Moyenne | J10: Récupérer les fichiers xlsx des publications ; demander les contours à l'Insee
A11: 7 | B11: Données statistiques | C11: Suivre la date de création des zones et leurs extensions | D11: Historique des contours des zones commerciales ; dates de construction des locaux (fichiers fonciers) | E11: Cerema | F11: EmpCom est figée en 2021 : impossible de dater l'arrivée d'une zone près d'un centre | G11: Fichiers fonciers sous convention | H11: Manquant | I11: Haute | J11: Reconstituer les dates via les fichiers fonciers ou Sitadel
A12: 8 | B12: Données statistiques | C12: Mesurer les flux de clients | D12: Fréquentation piétonne et flux de mobilité (comptages, données de téléphonie) | E12: Procos / Stackr, MyTraffic, Orange Flux Vision (privés) | F12: Mesurer la fréquentation des centres et des QPV avant et après l'ouverture d'une zone | G12: Payant | H12: Manquant | I12: Moyenne | J12: Partenariat ponctuel sur quelques villes tests
A13: 9 | B13: Données statistiques | C13: Comprendre les déplacements d'achat des habitants des QPV | D13: Enquêtes mobilité (EMP 2019, enquêtes ménages-déplacements locales) | E13: SDES / Insee ; Cerema et autorités organisatrices | F13: Mesurer la part des achats des habitants de QPV réalisés en périphérie | G13: Fichiers détail via ADISP / CASD ; enquêtes locales sur demande | H13: Manquant | I13: Moyenne | J13: Exploiter les enquêtes ménages-déplacements des grandes agglomérations
A14: 10 | B14: Données statistiques | C14: Contrôler le pouvoir d'achat local | D14: Revenus carroyés (Filosofi), revenus par QPV | E14: Insee | F14: Isoler l'effet du revenu, que la Cour des comptes cite comme première cause | G14: Ouvert | H14: Disponible, non intégré à notre analyse | I14: Moyenne | J14: Ajouter Filosofi aux modèles
A15: 11 | B15: Données statistiques | C15: Suivre les surfaces commerciales construites | D15: Sitadel (permis de construire, locaux commerciaux autorisés et commencés) | E15: SDES | F15: Mesurer la construction commerciale par commune et par année | G15: Ouvert | H15: Disponible, non intégré | I15: Moyenne | J15: Télécharger les séries communales de locaux d'activité
A16: 12 | B16: Données statistiques | C16: Suivre les grands magasins et leurs dates d'ouverture | D16: Base permanente des équipements (hypermarchés, supermarchés, grandes surfaces spécialisées) ; bases de points de vente (LSA Expert, Nielsen) | E16: Insee (BPE, ouverte) ; LSA, Nielsen (payant) | F16: Repérer les ouvertures de grandes surfaces avec leur format | G16: BPE ouverte ; bases privées payantes | H16: Partiel | I16: Moyenne | J16: Croiser la BPE annuelle avec Sirene
... A29: 25 | B29: Documents non consultés en intégralité | C29: Disposer des études historiques sur les quartiers | D29: CREDOC, « Commerces et zones urbaines sensibles » et « Le commerce dans les cités » | E29: CREDOC | F29: Données anciennes sur le commerce en ZUS | G29: Ouvert (PDF anciens) | H29: Non exploités (PDF illisibles) | I29: Basse | J29: Lire les PDF

Sheet Calculs propres (Sirene)
A1: Calculs propres sur le répertoire Sirene (non publiés)
A2: Ne pas mélanger avec l'état de l'art. Méthode et limites : analyse_commerce_territoires/rapport.html (dépôt du projet).
A4: N° | B4: Indicateur | C4: Valeur | D4: Unité | E4: Année(s) | F4: Champ | G4: Source des données
A5: 1 | B5: Commerces employeurs en zones périphériques (Cerema EmpCom) | C5: 28742 | D5: établissements | E5: 2012 | F5: 1 372 sites, tampon de 50 m ; NAF 47.1 à 47.7 ; employeurs | G5: Insee, Sirene (sept. 2026) ; Cerema, EmpCom ; ANCT, QPV 2024. Calculs propres.
A6: 2 | B6: Commerces employeurs en zones périphériques | C6: 35775 | D6: établissements | E6: 2025 | F6: Idem | G6: Insee, Sirene (sept. 2026) ; Cerema, EmpCom ; ANCT, QPV 2024. Calculs propres.
A7: 3 | B7: Évolution des commerces employeurs en zones périphériques | C7: 24.5 | D7: % | E7: 2012-2025 | F7: Idem | G7: Insee, Sirene (sept. 2026) ; Cerema, EmpCom ; ANCT, QPV 2024. Calculs propres.
A8: 4 | B8: Commerces employeurs dans les centres-villes | C8: 61526 | D8: établissements | E8: 2012 | F8: Cercle de 300 à 700 m autour de la mairie, 2 128 communes de 5 000 hab. et plus (hors Paris, Lyon, Marseille) | G8: Insee, Sirene (sept. 2026) ; Cerema, EmpCom ; ANCT, QPV 2024. Calculs propres.
A9: 5 | B9: Commerces employeurs dans les centres-villes | C9: 55973 | D9: établissements | E9: 2025 | F9: Idem | G9: Insee, Sirene (sept. 2026) ; Cerema, EmpCom ; ANCT, QPV 2024. Calculs propres.
A10: 6 | B10: Évolution des commerces employeurs dans les centres-villes | C10: -9 | D10: % | E10: 2012-2025 | F10: Idem | G10: Insee, Sirene (sept. 2026) ; Cerema, EmpCom ; ANCT, QPV 2024. Calculs propres.
A11: 7 | B11: Commerces employeurs dans les QPV | C11: 12964 | D11: établissements | E11: 2012 | F11: 1 362 QPV 2024 (code QPV de la géolocalisation Sirene) | G11: Insee, Sirene (sept. 2026) ; Cerema, EmpCom ; ANCT, QPV 2024. Calculs propres.
A12: 8 | B12: Commerces employeurs dans les QPV | C12: 12169 | D12: établissements | E12: 2025 | F12: Idem | G12: Insee, Sirene (sept. 2026) ; Cerema, EmpCom ; ANCT, QPV 2024. Calculs propres.
A13: 9 | B13: Évolution des commerces employeurs dans les QPV | C13: -6.1 | D13: % | E13: 2012-2025 | F13: Idem | G13: Insee, Sirene (sept. 2026) ; Cerema, EmpCom ; ANCT, QPV 2024. Calculs propres.
A14: 10 | B14: Évolution de tous les établissements (employeurs ou non) en zones périphériques | C14: 35.4 | D14: % | E14: 2012-2025 | F14: Idem, tous établissements actifs | G14: Insee, Sirene (sept. 2026) ; Cerema, EmpCom ; ANCT, QPV 2024. Calculs propres.
A15: 11 | B15: Évolution de tous les établissements dans les centres-villes | C15: -2.6 | D15: % | E15: 2012-2025 | F15: Idem | G15: Insee, Sirene (sept. 2026) ; Cerema, EmpCom ; ANCT, QPV 2024. Calculs propres.
A16: 12 | B16: Évolution de tous les établissements dans les QPV | C16: 4.6 | D16: % | E16: 2012-2025 | F16: Idem | G16: Insee, Sirene (sept. 2026) ; Cerema, EmpCom ; ANCT, QPV 2024. Calculs propres.
... A26: 22 | B26: Effet de la surface commerciale périphérique à moins de 10 km (modèle en coupe) | C26: -0.08 | D26: point par log-hectare | E26: 2012-2025 | F26: IC 95 % [−1,0 ; +0,9] : pas d'effet significatif | G26: Insee, Sirene (sept. 2026) ; Cerema, EmpCom ; ANCT, QPV 2024. Calculs propres.

Sheet Synthèse
A1: Synthèse
A2: Nombre de chiffres par thème et par niveau de vérification (calculé à partir de l'onglet « Chiffres »).
A4: Thème | B4: A - Relu | C4: B - Consulté | D4: C - Relais | E4: D - À vérifier | F4: E - Présentation | G4: Total
A5: 1. Poids des zones commerciales périphériques | B5: =COUNTIFS(Chiffres!$B$5:$B$468,$A5,Chiffres!$M$5:$M$468,"A - Relu dans la source primaire") -> 14 | C5: =COUNTIFS(Chiffres!$B$5:$B$468,$A5,Chiffres!$M$5:$M$468,"B - Source primaire consultée pendant la recherche (non relue)") -> 0 | D5: =COUNTIFS(Chiffres!$B$5:$B$468,$A5,Chiffres!$M$5:$M$468,"C - Via un relais (presse, synthèse, autre rapport)") -> 1 | E5: =COUNTIFS(Chiffres!$B$5:$B$468,$A5,Chiffres!$M$5:$M$468,"D - Non vérifié : origine à confirmer") -> 2 | F5: =COUNTIFS(Chiffres!$B$5:$B$468,$A5,Chiffres!$M$5:$M$468,"E - Repris de la présentation OCDE (non revérifié)") -> 3 | G5: =SUM(B5:F5) -> 20
A6: 2. Centres-villes : emploi et établissements | B6: =COUNTIFS(Chiffres!$B$5:$B$468,$A6,Chiffres!$M$5:$M$468,"A - Relu dans la source primaire") -> 18 | C6: =COUNTIFS(Chiffres!$B$5:$B$468,$A6,Chiffres!$M$5:$M$468,"B - Source primaire consultée pendant la recherche (non relue)") -> 0 | D6: =COUNTIFS(Chiffres!$B$5:$B$468,$A6,Chiffres!$M$5:$M$468,"C - Via un relais (presse, synthèse, autre rapport)") -> 0 | E6: =COUNTIFS(Chiffres!$B$5:$B$468,$A6,Chiffres!$M$5:$M$468,"D - Non vérifié : origine à confirmer") -> 0 | F6: =COUNTIFS(Chiffres!$B$5:$B$468,$A6,Chiffres!$M$5:$M$468,"E - Repris de la présentation OCDE (non revérifié)") -> 0 | G6: =SUM(B6:F6) -> 18
A7: 3. Centres-villes : vacance commerciale | B7: =COUNTIFS(Chiffres!$B$5:$B$468,$A7,Chiffres!$M$5:$M$468,"A - Relu dans la source primaire") -> 10 | C7: =COUNTIFS(Chiffres!$B$5:$B$468,$A7,Chiffres!$M$5:$M$468,"B - Source primaire consultée pendant la recherche (non relue)") -> 0 | D7: =COUNTIFS(Chiffres!$B$5:$B$468,$A7,Chiffres!$M$5:$M$468,"C - Via un relais (presse, synthèse, autre rapport)") -> 10 | E7: =COUNTIFS(Chiffres!$B$5:$B$468,$A7,Chiffres!$M$5:$M$468,"D - Non vérifié : origine à confirmer") -> 6 | F7: =COUNTIFS(Chiffres!$B$5:$B$468,$A7,Chiffres!$M$5:$M$468,"E - Repris de la présentation OCDE (non revérifié)") -> 1 | G7: =SUM(B7:F7) -> 27
A8: 4. Fréquentation, consommation, offre | B8: =COUNTIFS(Chiffres!$B$5:$B$468,$A8,Chiffres!$M$5:$M$468,"A - Relu dans la source primaire") -> 11 | C8: =COUNTIFS(Chiffres!$B$5:$B$468,$A8,Chiffres!$M$5:$M$468,"B - Source primaire consultée pendant la recherche (non relue)") -> 0 | D8: =COUNTIFS(Chiffres!$B$5:$B$468,$A8,Chiffres!$M$5:$M$468,"C - Via un relais (presse, synthèse, autre rapport)") -> 2 | E8: =COUNTIFS(Chiffres!$B$5:$B$468,$A8,Chiffres!$M$5:$M$468,"D - Non vérifié : origine à confirmer") -> 0 | F8: =COUNTIFS(Chiffres!$B$5:$B$468,$A8,Chiffres!$M$5:$M$468,"E - Repris de la présentation OCDE (non revérifié)") -> 0 | G8: =SUM(B8:F8) -> 13
A9: 5. QPV : commerce et contexte | B9: =COUNTIFS(Chiffres!$B$5:$B$468,$A9,Chiffres!$M$5:$M$468,"A - Relu dans la source primaire") -> 5 | C9: =COUNTIFS(Chiffres!$B$5:$B$468,$A9,Chiffres!$M$5:$M$468,"B - Source primaire consultée pendant la recherche (non relue)") -> 1 | D9: =COUNTIFS(Chiffres!$B$5:$B$468,$A9,Chiffres!$M$5:$M$468,"C - Via un relais (presse, synthèse, autre rapport)") -> 4 | E9: =COUNTIFS(Chiffres!$B$5:$B$468,$A9,Chiffres!$M$5:$M$468,"D - Non vérifié : origine à confirmer") -> 1 | F9: =COUNTIFS(Chiffres!$B$5:$B$468,$A9,Chiffres!$M$5:$M$468,"E - Repris de la présentation OCDE (non revérifié)") -> 0 | G9: =SUM(B9:F9) -> 11
A10: 6. Autorisations CDAC / CNAC | B10: =COUNTIFS(Chiffres!$B$5:$B$468,$A10,Chiffres!$M$5:$M$468,"A - Relu dans la source primaire") -> 15 | C10: =COUNTIFS(Chiffres!$B$5:$B$468,$A10,Chiffres!$M$5:$M$468,"B - Source primaire consultée pendant la recherche (non relue)") -> 0 | D10: =COUNTIFS(Chiffres!$B$5:$B$468,$A10,Chiffres!$M$5:$M$468,"C - Via un relais (presse, synthèse, autre rapport)") -> 3 | E10: =COUNTIFS(Chiffres!$B$5:$B$468,$A10,Chiffres!$M$5:$M$468,"D - Non vérifié : origine à confirmer") -> 0 | F10: =COUNTIFS(Chiffres!$B$5:$B$468,$A10,Chiffres!$M$5:$M$468,"E - Repris de la présentation OCDE (non revérifié)") -> 0 | G10: =SUM(B10:F10) -> 18
A11: 7. Cadre réglementaire (seuils) | B11: =COUNTIFS(Chiffres!$B$5:$B$468,$A11,Chiffres!$M$5:$M$468,"A - Relu dans la source primaire") -> 1 | C11: =COUNTIFS(Chiffres!$B$5:$B$468,$A11,Chiffres!$M$5:$M$468,"B - Source primaire consultée pendant la recherche (non relue)") -> 0 | D11: =COUNTIFS(Chiffres!$B$5:$B$468,$A11,Chiffres!$M$5:$M$468,"C - Via un relais (presse, synthèse, autre rapport)") -> 5 | E11: =COUNTIFS(Chiffres!$B$5:$B$468,$A11,Chiffres!$M$5:$M$468,"D - Non vérifié : origine à confirmer") -> 0 | F11: =COUNTIFS(Chiffres!$B$5:$B$468,$A11,Chiffres!$M$5:$M$468,"E - Repris de la présentation OCDE (non revérifié)") -> 0 | G11: =SUM(B11:F11) -> 6
A12: 8. Artificialisation et foncier | B12: =COUNTIFS(Chiffres!$B$5:$B$468,$A12,Chiffres!$M$5:$M$468,"A - Relu dans la source primaire") -> 4 | C12: =COUNTIFS(Chiffres!$B$5:$B$468,$A12,Chiffres!$M$5:$M$468,"B - Source primaire consultée pendant la recherche (non relue)") -> 0 | D12: =COUNTIFS(Chiffres!$B$5:$B$468,$A12,Chiffres!$M$5:$M$468,"C - Via un relais (presse, synthèse, autre rapport)") -> 0 | E12: =COUNTIFS(Chiffres!$B$5:$B$468,$A12,Chiffres!$M$5:$M$468,"D - Non vérifié : origine à confirmer") -> 1 | F12: =COUNTIFS(Chiffres!$B$5:$B$468,$A12,Chiffres!$M$5:$M$468,"E - Repris de la présentation OCDE (non revérifié)") -> 0 | G12: =SUM(B12:F12) -> 5
A13: 9. Périphérie : vacance et transformation | B13: =COUNTIFS(Chiffres!$B$5:$B$468,$A13,Chiffres!$M$5:$M$468,"A - Relu dans la source primaire") -> 11 | C13: =COUNTIFS(Chiffres!$B$5:$B$468,$A13,Chiffres!$M$5:$M$468,"B - Source primaire consultée pendant la recherche (non relue)") -> 0 | D13: =COUNTIFS(Chiffres!$B$5:$B$468,$A13,Chiffres!$M$5:$M$468,"C - Via un relais (presse, synthèse, autre rapport)") -> 6 | E13: =COUNTIFS(Chiffres!$B$5:$B$468,$A13,Chiffres!$M$5:$M$468,"D - Non vérifié : origine à confirmer") -> 0 | F13: =COUNTIFS(Chiffres!$B$5:$B$468,$A13,Chiffres!$M$5:$M$468,"E - Repris de la présentation OCDE (non revérifié)") -> 1 | G13: =SUM(B13:F13) -> 18
A14: 10. Politiques publiques : moyens et résultats | B14: =COUNTIFS(Chiffres!$B$5:$B$468,$A14,Chiffres!$M$5:$M$468,"A - Relu dans la source primaire") -> 19 | C14: =COUNTIFS(Chiffres!$B$5:$B$468,$A14,Chiffres!$M$5:$M$468,"B - Source primaire consultée pendant la recherche (non relue)") -> 0 | D14: =COUNTIFS(Chiffres!$B$5:$B$468,$A14,Chiffres!$M$5:$M$468,"C - Via un relais (presse, synthèse, autre rapport)") -> 1 | E14: =COUNTIFS(Chiffres!$B$5:$B$468,$A14,Chiffres!$M$5:$M$468,"D - Non vérifié : origine à confirmer") -> 5 | F14: =COUNTIFS(Chiffres!$B$5:$B$468,$A14,Chiffres!$M$5:$M$468,"E - Repris de la présentation OCDE (non revérifié)") -> 1 | G14: =SUM(B14:F14) -> 26
A15: 11. Littérature économique : effets mesurés | B15: =COUNTIFS(Chiffres!$B$5:$B$468,$A15,Chiffres!$M$5:$M$468,"A - Relu dans la source primaire") -> 0 | C15: =COUNTIFS(Chiffres!$B$5:$B$468,$A15,Chiffres!$M$5:$M$468,"B - Source primaire consultée pendant la recherche (non relue)") -> 0 | D15: =COUNTIFS(Chiffres!$B$5:$B$468,$A15,Chiffres!$M$5:$M$468,"C - Via un relais (presse, synthèse, autre rapport)") -> 2 | E15: =COUNTIFS(Chiffres!$B$5:$B$468,$A15,Chiffres!$M$5:$M$468,"D - Non vérifié : origine à confirmer") -> 0 | F15: =COUNTIFS(Chiffres!$B$5:$B$468,$A15,Chiffres!$M$5:$M$468,"E - Repris de la présentation OCDE (non revérifié)") -> 0 | G15: =SUM(B15:F15) -> 2
A16: Total | B16: =SUM(B5:B15) -> 108 | C16: =SUM(C5:C15) -> 1 | D16: =SUM(D5:D15) -> 34 | E16: =SUM(E5:E15) -> 15 | F16: =SUM(F5:F15) -> 6 | G16: =SUM(G5:G15) -> 164
A18: Légende complète des niveaux : onglet « Lisez-moi ».

Sheet Listes
A1: 1. Poids des zones commerciales périphériques | B1: Statistique publique | C1: A - Relu dans la source primaire
A2: 2. Centres-villes : emploi et établissements | B2: Rapport institutionnel (Cour des comptes, Parlement, inspections, mission) | C2: B - Source primaire consultée pendant la recherche (non relue)
A3: 3. Centres-villes : vacance commerciale | B3: Administration / opérateur public | C3: C - Via un relais (presse, synthèse, autre rapport)
A4: 4. Fréquentation, consommation, offre | B4: Fédération ou cabinet privé | C4: D - Non vérifié : origine à confirmer
A5: 5. QPV : commerce et contexte | B5: Presse / média spécialisé | C5: E - Repris de la présentation OCDE (non revérifié)
A6: 6. Autorisations CDAC / CNAC | B6: Recherche académique / CAE
A7: 7. Cadre réglementaire (seuils) | B7: Texte juridique
A8: 8. Artificialisation et foncier
A9: 9. Périphérie : vacance et transformation
A10: 10. Politiques publiques : moyens et résultats
A11: 11. Littérature économique : effets mesurés
